{
"meta":{"test_sets":[],"test_metrics":[],"learn_metrics":[{"best_value":"Min","name":"MultiClass"}],"launch_mode":"Train","parameters":"","iteration_count":1000,"learn_sets":["learn"],"name":"experiment"},
"iterations":[
{"learn":[1.08567336],"iteration":0,"passed_time":0.2025476931,"remaining_time":202.3451454},
{"learn":[1.075149896],"iteration":1,"passed_time":0.2915230564,"remaining_time":145.4700051},
{"learn":[1.066202072],"iteration":2,"passed_time":0.3745237309,"remaining_time":124.4667199},
{"learn":[1.05867609],"iteration":3,"passed_time":0.4539260838,"remaining_time":113.0275949},
{"learn":[1.052464894],"iteration":4,"passed_time":0.5415557232,"remaining_time":107.7695889},
{"learn":[1.046922453],"iteration":5,"passed_time":0.6271061201,"remaining_time":103.8905806},
{"learn":[1.042078152],"iteration":6,"passed_time":0.7089532444,"remaining_time":100.5700817},
{"learn":[1.037936629],"iteration":7,"passed_time":0.7887705283,"remaining_time":97.80754551},
{"learn":[1.034218882],"iteration":8,"passed_time":0.8704482724,"remaining_time":95.84602644},
{"learn":[1.030707964],"iteration":9,"passed_time":0.9477678252,"remaining_time":93.8290147},
{"learn":[1.027801213],"iteration":10,"passed_time":1.027234656,"remaining_time":92.35773404},
{"learn":[1.025253703],"iteration":11,"passed_time":1.115641963,"remaining_time":91.85452159},
{"learn":[1.022839433],"iteration":12,"passed_time":1.206100998,"remaining_time":91.57089887},
{"learn":[1.020760163],"iteration":13,"passed_time":1.285885884,"remaining_time":90.56310585},
{"learn":[1.01854967],"iteration":14,"passed_time":1.371011555,"remaining_time":90.0297588},
{"learn":[1.016179885],"iteration":15,"passed_time":1.46034859,"remaining_time":89.8114383},
{"learn":[1.01458602],"iteration":16,"passed_time":1.534280743,"remaining_time":88.71752764},
{"learn":[1.012999057],"iteration":17,"passed_time":1.605896678,"remaining_time":87.61058544},
{"learn":[1.011612066],"iteration":18,"passed_time":1.689930005,"remaining_time":87.25375446},
{"learn":[1.0104655],"iteration":19,"passed_time":1.770532575,"remaining_time":86.75609617},
{"learn":[1.00919556],"iteration":20,"passed_time":1.846793674,"remaining_time":86.09576223},
{"learn":[1.007917213],"iteration":21,"passed_time":1.922680042,"remaining_time":85.4718673},
{"learn":[1.006830095],"iteration":22,"passed_time":1.991385165,"remaining_time":84.59057855},
{"learn":[1.005419584],"iteration":23,"passed_time":2.074086218,"remaining_time":84.34617288},
{"learn":[1.00461579],"iteration":24,"passed_time":2.153436229,"remaining_time":83.98401292},
{"learn":[1.003891994],"iteration":25,"passed_time":2.226659992,"remaining_time":83.41410893},
{"learn":[1.003097744],"iteration":26,"passed_time":2.292245785,"remaining_time":82.60574625},
{"learn":[1.002102076],"iteration":27,"passed_time":2.362726149,"remaining_time":82.02035059},
{"learn":[1.000963591],"iteration":28,"passed_time":2.439554482,"remaining_time":81.68301385},
{"learn":[0.9994770035],"iteration":29,"passed_time":2.515248223,"remaining_time":81.32635923},
{"learn":[0.998759102],"iteration":30,"passed_time":2.586679992,"remaining_time":80.85461009},
{"learn":[0.9982020911],"iteration":31,"passed_time":2.651681778,"remaining_time":80.21337378},
{"learn":[0.9975817861],"iteration":32,"passed_time":2.730572912,"remaining_time":80.01406078},
{"learn":[0.9968903698],"iteration":33,"passed_time":2.80998793,"remaining_time":79.83671588},
{"learn":[0.9963711289],"iteration":34,"passed_time":2.881591711,"remaining_time":79.44960004},
{"learn":[0.9959179544],"iteration":35,"passed_time":2.954873933,"remaining_time":79.12495753},
{"learn":[0.9953335581],"iteration":36,"passed_time":3.029139435,"remaining_time":78.83949395},
{"learn":[0.9948306056],"iteration":37,"passed_time":3.101613716,"remaining_time":78.51979987},
{"learn":[0.9944145014],"iteration":38,"passed_time":3.168725527,"remaining_time":78.08064696},
{"learn":[0.9937841634],"iteration":39,"passed_time":3.239790392,"remaining_time":77.75496942},
{"learn":[0.9933176012],"iteration":40,"passed_time":3.311142859,"remaining_time":77.44843907},
{"learn":[0.9927833604],"iteration":41,"passed_time":3.385557969,"remaining_time":77.22296511},
{"learn":[0.9923298248],"iteration":42,"passed_time":3.454738375,"remaining_time":76.88801452},
{"learn":[0.9917951976],"iteration":43,"passed_time":3.532726284,"remaining_time":76.75650744},
{"learn":[0.9908803326],"iteration":44,"passed_time":3.601746927,"remaining_time":76.43707368},
{"learn":[0.9904803936],"iteration":45,"passed_time":3.671832902,"remaining_time":76.15062149},
{"learn":[0.9900817221],"iteration":46,"passed_time":3.749748647,"remaining_time":76.03213745},
{"learn":[0.9885523692],"iteration":47,"passed_time":3.832946966,"remaining_time":76.02011482},
{"learn":[0.9879827737],"iteration":48,"passed_time":3.925129402,"remaining_time":76.17955227},
{"learn":[0.9875552827],"iteration":49,"passed_time":3.997766486,"remaining_time":75.95756323},
{"learn":[0.9870257617],"iteration":50,"passed_time":4.088652392,"remaining_time":76.08100235},
{"learn":[0.9861533442],"iteration":51,"passed_time":4.159951405,"remaining_time":75.83911407},
{"learn":[0.985788749],"iteration":52,"passed_time":4.22841487,"remaining_time":75.55299778},
{"learn":[0.9854829883],"iteration":53,"passed_time":4.289143849,"remaining_time":75.13944595},
{"learn":[0.9850995733],"iteration":54,"passed_time":4.362323456,"remaining_time":74.95264847},
{"learn":[0.9843059422],"iteration":55,"passed_time":4.429587418,"remaining_time":74.67018791},
{"learn":[0.9840729524],"iteration":56,"passed_time":4.493344019,"remaining_time":74.33725281},
{"learn":[0.9830195579],"iteration":57,"passed_time":4.564917992,"remaining_time":74.14056463},
{"learn":[0.9826387191],"iteration":58,"passed_time":4.633517765,"remaining_time":73.90068164},
{"learn":[0.9822203331],"iteration":59,"passed_time":4.701921841,"remaining_time":73.66344218},
{"learn":[0.9816723485],"iteration":60,"passed_time":4.779045833,"remaining_time":73.56596782},
{"learn":[0.9810366095],"iteration":61,"passed_time":4.855431508,"remaining_time":73.45797991},
{"learn":[0.9806056277],"iteration":62,"passed_time":4.936247026,"remaining_time":73.41688037},
{"learn":[0.980286661],"iteration":63,"passed_time":5.007275059,"remaining_time":73.23139774},
{"learn":[0.9799237252],"iteration":64,"passed_time":5.076936196,"remaining_time":73.02977451},
{"learn":[0.9795176902],"iteration":65,"passed_time":5.146238866,"remaining_time":72.82707728},
{"learn":[0.9792487983],"iteration":66,"passed_time":5.215858557,"remaining_time":72.63277662},
{"learn":[0.9788145444],"iteration":67,"passed_time":5.28445003,"remaining_time":72.42805042},
{"learn":[0.9781359886],"iteration":68,"passed_time":5.353168406,"remaining_time":72.22898241},
{"learn":[0.9778838061],"iteration":69,"passed_time":5.42318505,"remaining_time":72.05088709},
{"learn":[0.9776697856],"iteration":70,"passed_time":5.495491943,"remaining_time":71.90580302},
{"learn":[0.9772377845],"iteration":71,"passed_time":5.570700426,"remaining_time":71.80013882},
{"learn":[0.9766368105],"iteration":72,"passed_time":5.637643943,"remaining_time":71.59035528},
{"learn":[0.9760970216],"iteration":73,"passed_time":5.704801583,"remaining_time":71.3871117},
{"learn":[0.9758008024],"iteration":74,"passed_time":5.788150439,"remaining_time":71.38718875},
{"learn":[0.9753428241],"iteration":75,"passed_time":5.8724296,"remaining_time":71.39638092},
{"learn":[0.9747797498],"iteration":76,"passed_time":5.956465359,"remaining_time":71.40022761},
{"learn":[0.9743738055],"iteration":77,"passed_time":6.040019994,"remaining_time":71.39613378},
{"learn":[0.9739322712],"iteration":78,"passed_time":6.119631837,"remaining_time":71.3440623},
{"learn":[0.9734748573],"iteration":79,"passed_time":6.190955988,"remaining_time":71.19599386},
{"learn":[0.973111825],"iteration":80,"passed_time":6.259004195,"remaining_time":71.01265253},
{"learn":[0.972706601],"iteration":81,"passed_time":6.328671829,"remaining_time":70.85025291},
{"learn":[0.9721950511],"iteration":82,"passed_time":6.40093527,"remaining_time":70.71876678},
{"learn":[0.9717823526],"iteration":83,"passed_time":6.470332838,"remaining_time":70.55743904},
{"learn":[0.9713479261],"iteration":84,"passed_time":6.550184412,"remaining_time":70.51080867},
{"learn":[0.9709155712],"iteration":85,"passed_time":6.624626574,"remaining_time":70.40591498},
{"learn":[0.9705398085],"iteration":86,"passed_time":6.692516703,"remaining_time":70.23296264},
{"learn":[0.9703411135],"iteration":87,"passed_time":6.75998189,"remaining_time":70.05799413},
{"learn":[0.9698810105],"iteration":88,"passed_time":6.830551243,"remaining_time":69.91721553},
{"learn":[0.9691799099],"iteration":89,"passed_time":6.907159734,"remaining_time":69.83905953},
{"learn":[0.9689329647],"iteration":90,"passed_time":6.981486072,"remaining_time":69.73814109},
{"learn":[0.9686225912],"iteration":91,"passed_time":7.056649168,"remaining_time":69.64605918},
{"learn":[0.9683784493],"iteration":92,"passed_time":7.139219101,"remaining_time":69.62657769},
{"learn":[0.968021699],"iteration":93,"passed_time":7.208850286,"remaining_time":69.48104637},
{"learn":[0.9676251302],"iteration":94,"passed_time":7.282628425,"remaining_time":69.37661815},
{"learn":[0.9673103491],"iteration":95,"passed_time":7.351606977,"remaining_time":69.22763236},
{"learn":[0.9669824069],"iteration":96,"passed_time":7.421091125,"remaining_time":69.08500294},
{"learn":[0.9667261239],"iteration":97,"passed_time":7.489945615,"remaining_time":68.93807087},
{"learn":[0.9663237131],"iteration":98,"passed_time":7.575412498,"remaining_time":68.94390566},
{"learn":[0.9660593049],"iteration":99,"passed_time":7.642208319,"remaining_time":68.77987487},
{"learn":[0.9657407266],"iteration":100,"passed_time":7.716803522,"remaining_time":68.68719174},
{"learn":[0.9651993742],"iteration":101,"passed_time":7.795008222,"remaining_time":68.62664101},
{"learn":[0.9648630862],"iteration":102,"passed_time":7.873633036,"remaining_time":68.56940615},
{"learn":[0.9646369846],"iteration":103,"passed_time":7.945152129,"remaining_time":68.45054142},
{"learn":[0.9641833253],"iteration":104,"passed_time":8.017300987,"remaining_time":68.3379465},
{"learn":[0.9638488619],"iteration":105,"passed_time":8.084687484,"remaining_time":68.18594915},
{"learn":[0.9634011438],"iteration":106,"passed_time":8.178675852,"remaining_time":68.25754706},
{"learn":[0.9630099167],"iteration":107,"passed_time":8.266898972,"remaining_time":68.27846188},
{"learn":[0.962694921],"iteration":108,"passed_time":8.349264286,"remaining_time":68.24949063},
{"learn":[0.9623716458],"iteration":109,"passed_time":8.425238235,"remaining_time":68.16783663},
{"learn":[0.9619617001],"iteration":110,"passed_time":8.514570568,"remaining_time":68.19327239},
{"learn":[0.9616241287],"iteration":111,"passed_time":8.591707742,"remaining_time":68.11996853},
{"learn":[0.9611597587],"iteration":112,"passed_time":8.666180391,"remaining_time":68.02568148},
{"learn":[0.960790422],"iteration":113,"passed_time":8.744565254,"remaining_time":67.9621475},
{"learn":[0.9604628484],"iteration":114,"passed_time":8.820670799,"remaining_time":67.88081441},
{"learn":[0.9601908783],"iteration":115,"passed_time":8.894488096,"remaining_time":67.78213342},
{"learn":[0.9598583609],"iteration":116,"passed_time":8.969604543,"remaining_time":67.69368215},
{"learn":[0.9594901834],"iteration":117,"passed_time":9.051363029,"remaining_time":67.65510332},
{"learn":[0.9591949768],"iteration":118,"passed_time":9.120254502,"remaining_time":67.52053963},
{"learn":[0.9589867861],"iteration":119,"passed_time":9.190060732,"remaining_time":67.3937787},
{"learn":[0.9585331819],"iteration":120,"passed_time":9.271367919,"remaining_time":67.35150744},
{"learn":[0.9582317327],"iteration":121,"passed_time":9.345243985,"remaining_time":67.25511655},
{"learn":[0.9578077024],"iteration":122,"passed_time":9.41673777,"remaining_time":67.14210589},
{"learn":[0.9573862895],"iteration":123,"passed_time":9.494569233,"remaining_time":67.07453748},
{"learn":[0.9570522842],"iteration":124,"passed_time":9.575889426,"remaining_time":67.03122599},
{"learn":[0.9567582358],"iteration":125,"passed_time":9.65358005,"remaining_time":66.96213463},
{"learn":[0.9562065469],"iteration":126,"passed_time":9.740793691,"remaining_time":66.95836923},
{"learn":[0.9554534418],"iteration":127,"passed_time":9.819432295,"remaining_time":66.89488251},
{"learn":[0.9550584451],"iteration":128,"passed_time":9.888731884,"remaining_time":66.76810443},
{"learn":[0.9547045796],"iteration":129,"passed_time":9.954083729,"remaining_time":66.61579111},
{"learn":[0.9544733535],"iteration":130,"passed_time":10.02132727,"remaining_time":66.47735421},
{"learn":[0.9542148232],"iteration":131,"passed_time":10.08801727,"remaining_time":66.33635599},
{"learn":[0.9537114817],"iteration":132,"passed_time":10.15867468,"remaining_time":66.22233798},
{"learn":[0.9533151675],"iteration":133,"passed_time":10.22952554,"remaining_time":66.11021729},
{"learn":[0.9529661522],"iteration":134,"passed_time":10.30639322,"remaining_time":66.03726026},
{"learn":[0.9527324621],"iteration":135,"passed_time":10.37258369,"remaining_time":65.89641406},
{"learn":[0.9523458152],"iteration":136,"passed_time":10.44268147,"remaining_time":65.78127087},
{"learn":[0.9518872665],"iteration":137,"passed_time":10.5140249,"remaining_time":65.67456135},
{"learn":[0.9514943008],"iteration":138,"passed_time":10.58495689,"remaining_time":65.56581213},
{"learn":[0.9512286028],"iteration":139,"passed_time":10.64693943,"remaining_time":65.40262791},
{"learn":[0.9507804365],"iteration":140,"passed_time":10.71844164,"remaining_time":65.29887496},
{"learn":[0.9504290468],"iteration":141,"passed_time":10.78354548,"remaining_time":65.15691566},
{"learn":[0.9499895606],"iteration":142,"passed_time":10.85888416,"remaining_time":65.07736871},
{"learn":[0.9493411819],"iteration":143,"passed_time":10.93186749,"remaining_time":64.98387895},
{"learn":[0.9488802007],"iteration":144,"passed_time":11.0079632,"remaining_time":64.90902439},
{"learn":[0.9483275959],"iteration":145,"passed_time":11.07738127,"remaining_time":64.79509318},
{"learn":[0.948076691],"iteration":146,"passed_time":11.14289583,"remaining_time":64.65911662},
{"learn":[0.9477932341],"iteration":147,"passed_time":11.20994523,"remaining_time":64.53292793},
{"learn":[0.9473045515],"iteration":148,"passed_time":11.28833775,"remaining_time":64.4723183},
{"learn":[0.947035616],"iteration":149,"passed_time":11.36281135,"remaining_time":64.38926434},
{"learn":[0.9465241413],"iteration":150,"passed_time":11.44369488,"remaining_time":64.34236391},
{"learn":[0.9461605959],"iteration":151,"passed_time":11.51684167,"remaining_time":64.25185354},
{"learn":[0.9456931693],"iteration":152,"passed_time":11.58557924,"remaining_time":64.13716088},
{"learn":[0.9453336741],"iteration":153,"passed_time":11.66028765,"remaining_time":64.05586594},
{"learn":[0.9447403697],"iteration":154,"passed_time":11.72760365,"remaining_time":63.93435537},
{"learn":[0.9445150057],"iteration":155,"passed_time":11.79875686,"remaining_time":63.83429991},
{"learn":[0.9440217968],"iteration":156,"passed_time":11.87341604,"remaining_time":63.7534377},
{"learn":[0.9435515136],"iteration":157,"passed_time":11.94821223,"remaining_time":63.67338418},
{"learn":[0.9432505218],"iteration":158,"passed_time":12.01740228,"remaining_time":63.56374416},
{"learn":[0.9428260509],"iteration":159,"passed_time":12.08658071,"remaining_time":63.45454874},
{"learn":[0.9424460089],"iteration":160,"passed_time":12.1557694,"remaining_time":63.34590388},
{"learn":[0.9420716179],"iteration":161,"passed_time":12.22737803,"remaining_time":63.25026412},
{"learn":[0.9417561348],"iteration":162,"passed_time":12.29445767,"remaining_time":63.13166298},
{"learn":[0.9414441463],"iteration":163,"passed_time":12.36510909,"remaining_time":63.03189753},
{"learn":[0.9411148529],"iteration":164,"passed_time":12.43389856,"remaining_time":62.92306241},
{"learn":[0.9406889024],"iteration":165,"passed_time":12.51152522,"remaining_time":62.85910865},
{"learn":[0.9405009383],"iteration":166,"passed_time":12.57990492,"remaining_time":62.74886704},
{"learn":[0.9402693349],"iteration":167,"passed_time":12.64739657,"remaining_time":62.63472588},
{"learn":[0.9399079864],"iteration":168,"passed_time":12.72100909,"remaining_time":62.55123405},
{"learn":[0.9394603461],"iteration":169,"passed_time":12.79679881,"remaining_time":62.47848832},
{"learn":[0.9391281823],"iteration":170,"passed_time":12.87495759,"remaining_time":62.41719207},
{"learn":[0.9388273489],"iteration":171,"passed_time":12.94294779,"remaining_time":62.30674868},
{"learn":[0.9386220086],"iteration":172,"passed_time":13.01982096,"remaining_time":62.23925974},
{"learn":[0.9382768973],"iteration":173,"passed_time":13.09129329,"remaining_time":62.14602448},
{"learn":[0.9378966565],"iteration":174,"passed_time":13.1600676,"remaining_time":62.04031869},
{"learn":[0.9375979647],"iteration":175,"passed_time":13.22718093,"remaining_time":61.92725615},
{"learn":[0.9372919319],"iteration":176,"passed_time":13.29713009,"remaining_time":61.82789866},
{"learn":[0.9370569818],"iteration":177,"passed_time":13.36372301,"remaining_time":61.71337254},
{"learn":[0.9367861375],"iteration":178,"passed_time":13.43232021,"remaining_time":61.6085748},
{"learn":[0.9363396371],"iteration":179,"passed_time":13.50408902,"remaining_time":61.51862778},
{"learn":[0.93590816],"iteration":180,"passed_time":13.57221268,"remaining_time":61.41238775},
{"learn":[0.9354990298],"iteration":181,"passed_time":13.65342719,"remaining_time":61.36540352},
{"learn":[0.9349673408],"iteration":182,"passed_time":13.73140092,"remaining_time":61.3035768},
{"learn":[0.9348062136],"iteration":183,"passed_time":13.79648687,"remaining_time":61.18442004},
{"learn":[0.9344871485],"iteration":184,"passed_time":13.86160463,"remaining_time":61.06598797},
{"learn":[0.9339874757],"iteration":185,"passed_time":13.93571691,"remaining_time":60.98749229},
{"learn":[0.9334505864],"iteration":186,"passed_time":14.02241909,"remaining_time":60.96377923},
{"learn":[0.9330304479],"iteration":187,"passed_time":14.09281228,"remaining_time":60.86895517},
{"learn":[0.9327743432],"iteration":188,"passed_time":14.15639518,"remaining_time":60.74516661},
{"learn":[0.932419878],"iteration":189,"passed_time":14.22525823,"remaining_time":60.64452194},
{"learn":[0.9320543771],"iteration":190,"passed_time":14.29481721,"remaining_time":60.54715771},
{"learn":[0.9316418732],"iteration":191,"passed_time":14.36604567,"remaining_time":60.45710885},
{"learn":[0.9313351939],"iteration":192,"passed_time":14.43466109,"remaining_time":60.356329},
{"learn":[0.931063877],"iteration":193,"passed_time":14.50371449,"remaining_time":60.25770042},
{"learn":[0.9307523489],"iteration":194,"passed_time":14.57071528,"remaining_time":60.15090153},
{"learn":[0.9302648126],"iteration":195,"passed_time":14.64439394,"remaining_time":60.07190169},
{"learn":[0.9297208169],"iteration":196,"passed_time":14.73174434,"remaining_time":60.04868376},
{"learn":[0.9292681127],"iteration":197,"passed_time":14.80274893,"remaining_time":59.95860932},
{"learn":[0.9289467446],"iteration":198,"passed_time":14.87145333,"remaining_time":59.85946792},
{"learn":[0.9285731647],"iteration":199,"passed_time":14.94600417,"remaining_time":59.78401669},
{"learn":[0.928210158],"iteration":200,"passed_time":15.01567419,"remaining_time":59.68917251},
{"learn":[0.9278697669],"iteration":201,"passed_time":15.08619453,"remaining_time":59.59793682},
{"learn":[0.9275835272],"iteration":202,"passed_time":15.15262148,"remaining_time":59.49083409},
{"learn":[0.9271785738],"iteration":203,"passed_time":15.22042105,"remaining_time":59.38948607},
{"learn":[0.9266466873],"iteration":204,"passed_time":15.29334776,"remaining_time":59.30834863},
{"learn":[0.926197631],"iteration":205,"passed_time":15.36462826,"remaining_time":59.22094581},
{"learn":[0.9258987829],"iteration":206,"passed_time":15.43682197,"remaining_time":59.13719719},
{"learn":[0.9254932547],"iteration":207,"passed_time":15.51149543,"remaining_time":59.06300181},
{"learn":[0.9251173513],"iteration":208,"passed_time":15.58091164,"remaining_time":58.96890483},
{"learn":[0.9247034256],"iteration":209,"passed_time":15.65582635,"remaining_time":58.8957277},
{"learn":[0.9243361991],"iteration":210,"passed_time":15.73502715,"remaining_time":58.83856125},
{"learn":[0.9239758796],"iteration":211,"passed_time":15.81465372,"remaining_time":58.78276947},
{"learn":[0.9236154629],"iteration":212,"passed_time":15.88707106,"remaining_time":58.70011701},
{"learn":[0.9232652188],"iteration":213,"passed_time":15.95787807,"remaining_time":58.61164563},
{"learn":[0.922981593],"iteration":214,"passed_time":16.02382734,"remaining_time":58.50560216},
{"learn":[0.9222618612],"iteration":215,"passed_time":16.10136235,"remaining_time":58.44198186},
{"learn":[0.921806873],"iteration":216,"passed_time":16.17796728,"remaining_time":58.37487735},
{"learn":[0.9213993058],"iteration":217,"passed_time":16.24964894,"remaining_time":58.29002511},
{"learn":[0.9210188977],"iteration":218,"passed_time":16.32404799,"remaining_time":58.21498392},
{"learn":[0.9207511827],"iteration":219,"passed_time":16.39678473,"remaining_time":58.13405494},
{"learn":[0.920263412],"iteration":220,"passed_time":16.46625095,"remaining_time":58.04167191},
{"learn":[0.9198953837],"iteration":221,"passed_time":16.53631585,"remaining_time":57.9515934},
{"learn":[0.9194657146],"iteration":222,"passed_time":16.6174866,"remaining_time":57.90039053},
{"learn":[0.9190700341],"iteration":223,"passed_time":16.68787899,"remaining_time":57.81158078},
{"learn":[0.9187758041],"iteration":224,"passed_time":16.76179631,"remaining_time":57.73507617},
{"learn":[0.9186325855],"iteration":225,"passed_time":16.83781273,"remaining_time":57.66578342},
{"learn":[0.9184072339],"iteration":226,"passed_time":16.91323408,"remaining_time":57.59440503},
{"learn":[0.9180059312],"iteration":227,"passed_time":16.98531073,"remaining_time":57.51166615},
{"learn":[0.9176039861],"iteration":228,"passed_time":17.06028453,"remaining_time":57.43877457},
{"learn":[0.9172823594],"iteration":229,"passed_time":17.12730127,"remaining_time":57.33922599},
{"learn":[0.917021162],"iteration":230,"passed_time":17.19311884,"remaining_time":57.23596703},
{"learn":[0.9167789113],"iteration":231,"passed_time":17.2614613,"remaining_time":57.14138914},
{"learn":[0.9164285958],"iteration":232,"passed_time":17.32537545,"remaining_time":57.03245909},
{"learn":[0.9159489732],"iteration":233,"passed_time":17.39729953,"remaining_time":56.95013435},
{"learn":[0.9156671707],"iteration":234,"passed_time":17.47126479,"remaining_time":56.87454282},
{"learn":[0.9153236475],"iteration":235,"passed_time":17.5458443,"remaining_time":56.80095358},
{"learn":[0.9149698011],"iteration":236,"passed_time":17.61421936,"remaining_time":56.7073813},
{"learn":[0.91464875],"iteration":237,"passed_time":17.68559628,"remaining_time":56.62363179},
{"learn":[0.9143472353],"iteration":238,"passed_time":17.76115751,"remaining_time":56.55330906},
{"learn":[0.9140000122],"iteration":239,"passed_time":17.83768463,"remaining_time":56.48600133},
{"learn":[0.9137067537],"iteration":240,"passed_time":17.91538888,"remaining_time":56.42232432},
{"learn":[0.9133810469],"iteration":241,"passed_time":18.00220467,"remaining_time":56.38707083},
{"learn":[0.9130579557],"iteration":242,"passed_time":18.09210295,"remaining_time":56.3609956},
{"learn":[0.9127539368],"iteration":243,"passed_time":18.16640388,"remaining_time":56.28607105},
{"learn":[0.9123815563],"iteration":244,"passed_time":18.23722067,"remaining_time":56.20041472},
{"learn":[0.9120829011],"iteration":245,"passed_time":18.31525048,"remaining_time":56.13698723},
{"learn":[0.9116642434],"iteration":246,"passed_time":18.40004424,"remaining_time":56.094062},
{"learn":[0.9113170506],"iteration":247,"passed_time":18.4769106,"remaining_time":56.02676117},
{"learn":[0.9110372335],"iteration":248,"passed_time":18.5530003,"remaining_time":55.95704108},
{"learn":[0.9107986206],"iteration":249,"passed_time":18.62403202,"remaining_time":55.87209607},
{"learn":[0.9105748714],"iteration":250,"passed_time":18.70025835,"remaining_time":55.80276297},
{"learn":[0.9102926002],"iteration":251,"passed_time":18.78472739,"remaining_time":55.75784163},
{"learn":[0.9100381774],"iteration":252,"passed_time":18.85457635,"remaining_time":55.66944083},
{"learn":[0.9095228912],"iteration":253,"passed_time":18.93741445,"remaining_time":55.61933537},
{"learn":[0.9092012115],"iteration":254,"passed_time":19.02363698,"remaining_time":55.57886099},
{"learn":[0.9089947927],"iteration":255,"passed_time":19.10270654,"remaining_time":55.51724089},
{"learn":[0.9087505332],"iteration":256,"passed_time":19.17014263,"remaining_time":55.42185205},
{"learn":[0.9084536341],"iteration":257,"passed_time":19.24430486,"remaining_time":55.34602406},
{"learn":[0.9082773857],"iteration":258,"passed_time":19.31874356,"remaining_time":55.27099992},
{"learn":[0.9078029327],"iteration":259,"passed_time":19.39793979,"remaining_time":55.20952093},
{"learn":[0.9074705952],"iteration":260,"passed_time":19.47849243,"remaining_time":55.15174678},
{"learn":[0.9070647824],"iteration":261,"passed_time":19.56347403,"remaining_time":55.10627417},
{"learn":[0.9067114052],"iteration":262,"passed_time":19.63952173,"remaining_time":55.03546584},
{"learn":[0.906316581],"iteration":263,"passed_time":19.7155526,"remaining_time":54.96457089},
{"learn":[0.9059585688],"iteration":264,"passed_time":19.79677135,"remaining_time":54.90802621},
{"learn":[0.9055418017],"iteration":265,"passed_time":19.87576723,"remaining_time":54.8451622},
{"learn":[0.9051512285],"iteration":266,"passed_time":19.95149685,"remaining_time":54.77321046},
{"learn":[0.904692597],"iteration":267,"passed_time":20.03404051,"remaining_time":54.71984199},
{"learn":[0.9044117724],"iteration":268,"passed_time":20.10710331,"remaining_time":54.64049264},
{"learn":[0.9043334133],"iteration":269,"passed_time":20.18585686,"remaining_time":54.57657595},
{"learn":[0.9041054214],"iteration":270,"passed_time":20.25896302,"remaining_time":54.49735809},
{"learn":[0.9037583729],"iteration":271,"passed_time":20.33624646,"remaining_time":54.42936551},
{"learn":[0.903484918],"iteration":272,"passed_time":20.40906995,"remaining_time":54.34942803},
{"learn":[0.903121236],"iteration":273,"passed_time":20.49114738,"remaining_time":54.29406202},
{"learn":[0.9027643587],"iteration":274,"passed_time":20.56888145,"remaining_time":54.2270511},
{"learn":[0.9024938589],"iteration":275,"passed_time":20.65379793,"remaining_time":54.17880326},
{"learn":[0.9019713285],"iteration":276,"passed_time":20.73918037,"remaining_time":54.13150688},
{"learn":[0.9014926126],"iteration":277,"passed_time":20.82563463,"remaining_time":54.08672015},
{"learn":[0.9012593179],"iteration":278,"passed_time":20.90250177,"remaining_time":54.0168594},
{"learn":[0.9009876829],"iteration":279,"passed_time":20.98522662,"remaining_time":53.9620113},
{"learn":[0.9007194056],"iteration":280,"passed_time":21.05857571,"remaining_time":53.88297487},
{"learn":[0.9004220101],"iteration":281,"passed_time":21.13777104,"remaining_time":53.81886386},
{"learn":[0.9000614797],"iteration":282,"passed_time":21.21468353,"remaining_time":53.74886252},
{"learn":[0.8997672524],"iteration":283,"passed_time":21.2972898,"remaining_time":53.69316724},
{"learn":[0.8992385725],"iteration":284,"passed_time":21.37989706,"remaining_time":53.63728562},
{"learn":[0.8989383388],"iteration":285,"passed_time":21.45696407,"remaining_time":53.56738583},
{"learn":[0.8986762989],"iteration":286,"passed_time":21.53459578,"remaining_time":53.498839},
{"learn":[0.8984370944],"iteration":287,"passed_time":21.61030712,"remaining_time":53.42548149},
{"learn":[0.8980893771],"iteration":288,"passed_time":21.68880905,"remaining_time":53.35897313},
{"learn":[0.8978452422],"iteration":289,"passed_time":21.76481448,"remaining_time":53.28626993},
{"learn":[0.8975010265],"iteration":290,"passed_time":21.84714075,"remaining_time":53.2289443},
{"learn":[0.8973597554],"iteration":291,"passed_time":21.9254258,"remaining_time":53.16164886},
{"learn":[0.8970329415],"iteration":292,"passed_time":22.00386132,"remaining_time":53.09464148},
{"learn":[0.8966821463],"iteration":293,"passed_time":22.08017221,"remaining_time":53.02245436},
{"learn":[0.8965207954],"iteration":294,"passed_time":22.15323971,"remaining_time":52.94248812},
{"learn":[0.8962306553],"iteration":295,"passed_time":22.22461191,"remaining_time":52.85853644},
{"learn":[0.8959556304],"iteration":296,"passed_time":22.2960835,"remaining_time":52.77490471},
{"learn":[0.8955613989],"iteration":297,"passed_time":22.37717059,"remaining_time":52.71400589},
{"learn":[0.8950648576],"iteration":298,"passed_time":22.46748324,"remaining_time":52.67460117},
{"learn":[0.8946707147],"iteration":299,"passed_time":22.55378478,"remaining_time":52.62549783},
{"learn":[0.894345912],"iteration":300,"passed_time":22.62294578,"remaining_time":52.53634254},
{"learn":[0.8941747342],"iteration":301,"passed_time":22.69197113,"remaining_time":52.44700612},
{"learn":[0.893834071],"iteration":302,"passed_time":22.76721814,"remaining_time":52.37211567},
{"learn":[0.8933797793],"iteration":303,"passed_time":22.8452723,"remaining_time":52.30364975},
{"learn":[0.89291224],"iteration":304,"passed_time":22.92465969,"remaining_time":52.23815897},
{"learn":[0.8926551665],"iteration":305,"passed_time":23.00375145,"remaining_time":52.17190689},
{"learn":[0.8924079365],"iteration":306,"passed_time":23.07304955,"remaining_time":52.08346364},
{"learn":[0.8923115263],"iteration":307,"passed_time":23.14202871,"remaining_time":51.99442813},
{"learn":[0.8920289601],"iteration":308,"passed_time":23.21462381,"remaining_time":51.91360857},
{"learn":[0.891586691],"iteration":309,"passed_time":23.30508246,"remaining_time":51.87260289},
{"learn":[0.8912300611],"iteration":310,"passed_time":23.38000582,"remaining_time":51.79686178},
{"learn":[0.8907556217],"iteration":311,"passed_time":23.46851997,"remaining_time":51.75109531},
{"learn":[0.8904802142],"iteration":312,"passed_time":23.58549763,"remaining_time":51.76752994},
{"learn":[0.8903919572],"iteration":313,"passed_time":23.65505625,"remaining_time":51.67951779},
{"learn":[0.890131398],"iteration":314,"passed_time":23.73419288,"remaining_time":51.61245118},
{"learn":[0.8898735149],"iteration":315,"passed_time":23.80675831,"remaining_time":51.53108445},
{"learn":[0.8896734944],"iteration":316,"passed_time":23.88411147,"remaining_time":51.46008875},
{"learn":[0.8893395656],"iteration":317,"passed_time":23.9597006,"remaining_time":51.38526985},
{"learn":[0.8891864341],"iteration":318,"passed_time":24.03503329,"remaining_time":51.30989865},
{"learn":[0.8889101322],"iteration":319,"passed_time":24.10670278,"remaining_time":51.22674341},
{"learn":[0.8885878788],"iteration":320,"passed_time":24.18160141,"remaining_time":51.15049021},
{"learn":[0.888277755],"iteration":321,"passed_time":24.25861527,"remaining_time":51.07869924},
{"learn":[0.887850386],"iteration":322,"passed_time":24.33332631,"remaining_time":51.00204926},
{"learn":[0.8875903941],"iteration":323,"passed_time":24.4180034,"remaining_time":50.94620462},
{"learn":[0.887461833],"iteration":324,"passed_time":24.48676839,"remaining_time":50.85713434},
{"learn":[0.8871643953],"iteration":325,"passed_time":24.56130013,"remaining_time":50.78011131},
{"learn":[0.8868477312],"iteration":326,"passed_time":24.63971963,"remaining_time":50.71110492},
{"learn":[0.886627849],"iteration":327,"passed_time":24.71775848,"remaining_time":50.64126127},
{"learn":[0.8863441675],"iteration":328,"passed_time":24.79123826,"remaining_time":50.56206951},
{"learn":[0.8859797414],"iteration":329,"passed_time":24.87008728,"remaining_time":50.49381357},
{"learn":[0.8857049999],"iteration":330,"passed_time":24.94794856,"remaining_time":50.42349725},
{"learn":[0.8854431587],"iteration":331,"passed_time":25.02470433,"remaining_time":50.35091112},
{"learn":[0.8852036075],"iteration":332,"passed_time":25.10046396,"remaining_time":50.27630469},
{"learn":[0.884882885],"iteration":333,"passed_time":25.17688852,"remaining_time":50.20301724},
{"learn":[0.8845986179],"iteration":334,"passed_time":25.26123219,"remaining_time":50.14543106},
{"learn":[0.8843005724],"iteration":335,"passed_time":25.34499505,"remaining_time":50.08653783},
{"learn":[0.8840599868],"iteration":336,"passed_time":25.416022,"remaining_time":50.00244091},
{"learn":[0.8838237949],"iteration":337,"passed_time":25.49339551,"remaining_time":49.93085157},
{"learn":[0.8834653331],"iteration":338,"passed_time":25.57216211,"remaining_time":49.8619444},
{"learn":[0.8831365844],"iteration":339,"passed_time":25.65022482,"remaining_time":49.79161288},
{"learn":[0.8827859389],"iteration":340,"passed_time":25.73653904,"remaining_time":49.73718249},
{"learn":[0.8823172305],"iteration":341,"passed_time":25.82834931,"remaining_time":49.6931399},
{"learn":[0.881912749],"iteration":342,"passed_time":25.91278069,"remaining_time":49.63468488},
{"learn":[0.8814323838],"iteration":343,"passed_time":26.02765865,"remaining_time":49.63413976},
{"learn":[0.8811735266],"iteration":344,"passed_time":26.10571055,"remaining_time":49.56301569},
{"learn":[0.8807625557],"iteration":345,"passed_time":26.18397023,"remaining_time":49.4922443},
{"learn":[0.8804873116],"iteration":346,"passed_time":26.2633909,"remaining_time":49.42361457},
{"learn":[0.8801029702],"iteration":347,"passed_time":26.33849159,"remaining_time":49.34682908},
{"learn":[0.8796217111],"iteration":348,"passed_time":26.4125633,"remaining_time":49.26813384},
{"learn":[0.8793020108],"iteration":349,"passed_time":26.4874594,"remaining_time":49.19099603},
{"learn":[0.8789946323],"iteration":350,"passed_time":26.57260361,"remaining_time":49.13281979},
{"learn":[0.8786213263],"iteration":351,"passed_time":26.64782966,"remaining_time":49.05623188},
{"learn":[0.8783212178],"iteration":352,"passed_time":26.72373123,"remaining_time":48.98088982},
{"learn":[0.878013426],"iteration":353,"passed_time":26.80768532,"remaining_time":48.92023931},
{"learn":[0.8777757362],"iteration":354,"passed_time":26.88824053,"remaining_time":48.85328209},
{"learn":[0.8775023066],"iteration":355,"passed_time":26.97251555,"remaining_time":48.79297757},
{"learn":[0.8773355819],"iteration":356,"passed_time":27.04704599,"remaining_time":48.71498759},
{"learn":[0.8771213811],"iteration":357,"passed_time":27.11955103,"remaining_time":48.63338481},
{"learn":[0.8767559617],"iteration":358,"passed_time":27.19261592,"remaining_time":48.55283232},
{"learn":[0.8765107493],"iteration":359,"passed_time":27.26792819,"remaining_time":48.47631678},
{"learn":[0.8761742535],"iteration":360,"passed_time":27.34585379,"remaining_time":48.40443372},
{"learn":[0.8760019767],"iteration":361,"passed_time":27.42438056,"remaining_time":48.33357679},
{"learn":[0.8756977058],"iteration":362,"passed_time":27.50385679,"remaining_time":48.26434373},
{"learn":[0.8753751645],"iteration":363,"passed_time":27.58082467,"remaining_time":48.19067168},
{"learn":[0.8749361867],"iteration":364,"passed_time":27.65663777,"remaining_time":48.11497255},
{"learn":[0.8746214308],"iteration":365,"passed_time":27.7323908,"remaining_time":48.03916876},
{"learn":[0.8743158154],"iteration":366,"passed_time":27.81240517,"remaining_time":47.97071519},
{"learn":[0.87384553],"iteration":367,"passed_time":27.89892324,"remaining_time":47.91336818},
{"learn":[0.873668815],"iteration":368,"passed_time":27.98319177,"remaining_time":47.85201628},
{"learn":[0.8733531219],"iteration":369,"passed_time":28.06336084,"remaining_time":47.78356036},
{"learn":[0.873132362],"iteration":370,"passed_time":28.13553479,"remaining_time":47.70148621},
{"learn":[0.87295903],"iteration":371,"passed_time":28.20695238,"remaining_time":47.61818843},
{"learn":[0.8725782347],"iteration":372,"passed_time":28.28672647,"remaining_time":47.54900133},
{"learn":[0.8724336501],"iteration":373,"passed_time":28.36101007,"remaining_time":47.47056765},
{"learn":[0.8721918869],"iteration":374,"passed_time":28.43481403,"remaining_time":47.39135672},
{"learn":[0.8718660189],"iteration":375,"passed_time":28.51757973,"remaining_time":47.32704721},
{"learn":[0.8715514745],"iteration":376,"passed_time":28.5931567,"remaining_time":47.25076028},
{"learn":[0.8711745009],"iteration":377,"passed_time":28.67058077,"remaining_time":47.1775165},
{"learn":[0.8709898076],"iteration":378,"passed_time":28.74263167,"remaining_time":47.09544662},
{"learn":[0.870827959],"iteration":379,"passed_time":28.81135809,"remaining_time":47.00800531},
{"learn":[0.8705896567],"iteration":380,"passed_time":28.88123873,"remaining_time":46.92253746},
{"learn":[0.870308482],"iteration":381,"passed_time":28.95942415,"remaining_time":46.85058672},
{"learn":[0.8699820385],"iteration":382,"passed_time":29.03743984,"remaining_time":46.77832998},
{"learn":[0.8697024651],"iteration":383,"passed_time":29.11376972,"remaining_time":46.70333893},
{"learn":[0.8693576139],"iteration":384,"passed_time":29.19519791,"remaining_time":46.63648497},
{"learn":[0.8691051004],"iteration":385,"passed_time":29.27411404,"remaining_time":46.56555965},
{"learn":[0.8687961446],"iteration":386,"passed_time":29.3533891,"remaining_time":46.49516154},
{"learn":[0.8685278095],"iteration":387,"passed_time":29.43158038,"remaining_time":46.42300822},
{"learn":[0.8682960016],"iteration":388,"passed_time":29.51091696,"remaining_time":46.35262279},
{"learn":[0.868054595],"iteration":389,"passed_time":29.58673974,"remaining_time":46.27669549},
{"learn":[0.8676110053],"iteration":390,"passed_time":29.66754698,"remaining_time":46.20853225},
{"learn":[0.8673278549],"iteration":391,"passed_time":29.74093133,"remaining_time":46.12879145},
{"learn":[0.8671271443],"iteration":392,"passed_time":29.81622649,"remaining_time":46.05203431},
{"learn":[0.8667624092],"iteration":393,"passed_time":29.88944009,"remaining_time":45.97208298},
{"learn":[0.8663757667],"iteration":394,"passed_time":29.97412218,"remaining_time":45.90973144},
{"learn":[0.8660421136],"iteration":395,"passed_time":30.05449006,"remaining_time":45.84068686},
{"learn":[0.8658648925],"iteration":396,"passed_time":30.13262931,"remaining_time":45.76820019},
{"learn":[0.8654650975],"iteration":397,"passed_time":30.2108234,"remaining_time":45.69576805},
{"learn":[0.8650876493],"iteration":398,"passed_time":30.28783853,"remaining_time":45.62153122},
{"learn":[0.8647858102],"iteration":399,"passed_time":30.36533974,"remaining_time":45.54800961},
{"learn":[0.8645406217],"iteration":400,"passed_time":30.43890538,"remaining_time":45.46858933},
{"learn":[0.8642992792],"iteration":401,"passed_time":30.52236621,"remaining_time":45.40391789},
{"learn":[0.8639085914],"iteration":402,"passed_time":30.6015798,"remaining_time":45.3328614},
{"learn":[0.863753383],"iteration":403,"passed_time":30.67933486,"remaining_time":45.25961282},
{"learn":[0.8635026175],"iteration":404,"passed_time":30.75200129,"remaining_time":45.1788661},
{"learn":[0.8632033953],"iteration":405,"passed_time":30.83264146,"remaining_time":45.1098252},
{"learn":[0.8627989979],"iteration":406,"passed_time":30.91409921,"remaining_time":45.04191851},
{"learn":[0.8626528943],"iteration":407,"passed_time":30.99020503,"remaining_time":44.96617985},
{"learn":[0.8623692567],"iteration":408,"passed_time":31.06990958,"remaining_time":44.89563951},
{"learn":[0.8620088087],"iteration":409,"passed_time":31.15137008,"remaining_time":44.82758134},
{"learn":[0.8617649115],"iteration":410,"passed_time":31.23876368,"remaining_time":44.7679606},
{"learn":[0.8615628079],"iteration":411,"passed_time":31.31196029,"remaining_time":44.68794333},
{"learn":[0.8613813427],"iteration":412,"passed_time":31.38185904,"remaining_time":44.60327181},
{"learn":[0.8611287621],"iteration":413,"passed_time":31.4545019,"remaining_time":44.52255582},
{"learn":[0.860732839],"iteration":414,"passed_time":31.53864003,"remaining_time":44.45808294},
{"learn":[0.8604952918],"iteration":415,"passed_time":31.61956348,"remaining_time":44.38900258},
{"learn":[0.860296043],"iteration":416,"passed_time":31.69408438,"remaining_time":44.31091413},
{"learn":[0.8601635307],"iteration":417,"passed_time":31.76401534,"remaining_time":44.22645198},
{"learn":[0.8598469407],"iteration":418,"passed_time":31.84306928,"remaining_time":44.15470943},
{"learn":[0.8595244276],"iteration":419,"passed_time":31.92097275,"remaining_time":44.08134333},
{"learn":[0.8593308823],"iteration":420,"passed_time":31.9988282,"remaining_time":44.00788961},
{"learn":[0.8591365584],"iteration":421,"passed_time":32.07455826,"remaining_time":43.93150397},
{"learn":[0.8589826491],"iteration":422,"passed_time":32.15424284,"remaining_time":43.86051565},
{"learn":[0.8587159074],"iteration":423,"passed_time":32.23673584,"remaining_time":43.79330152},
{"learn":[0.8584396544],"iteration":424,"passed_time":32.33120996,"remaining_time":43.74222524},
{"learn":[0.8580507439],"iteration":425,"passed_time":32.4283508,"remaining_time":43.6945384},
{"learn":[0.8578676017],"iteration":426,"passed_time":32.51213313,"remaining_time":43.62869387},
{"learn":[0.8576521328],"iteration":427,"passed_time":32.59313125,"remaining_time":43.55904457},
{"learn":[0.857473589],"iteration":428,"passed_time":32.67926707,"remaining_time":43.49618064},
{"learn":[0.8571189319],"iteration":429,"passed_time":32.76366626,"remaining_time":43.43090643},
{"learn":[0.8566799949],"iteration":430,"passed_time":32.85355659,"remaining_time":43.37279281},
{"learn":[0.8563952748],"iteration":431,"passed_time":32.93618442,"remaining_time":43.30498322},
{"learn":[0.8561304604],"iteration":432,"passed_time":33.00971304,"remaining_time":43.22519006},
{"learn":[0.8559304154],"iteration":433,"passed_time":33.08533233,"remaining_time":43.1481523},
{"learn":[0.855490698],"iteration":434,"passed_time":33.17142924,"remaining_time":43.08472993},
{"learn":[0.8552426112],"iteration":435,"passed_time":33.25037869,"remaining_time":43.01195776},
{"learn":[0.8549616042],"iteration":436,"passed_time":33.335078,"remaining_time":42.94656502},
{"learn":[0.8546464174],"iteration":437,"passed_time":33.44045109,"remaining_time":42.90761076},
{"learn":[0.8543115491],"iteration":438,"passed_time":33.52595855,"remaining_time":42.84296753},
{"learn":[0.8539812253],"iteration":439,"passed_time":33.60690238,"remaining_time":42.77242121},
{"learn":[0.8535448206],"iteration":440,"passed_time":33.69409806,"remaining_time":42.70975241},
{"learn":[0.8532575302],"iteration":441,"passed_time":33.76878649,"remaining_time":42.63118294},
{"learn":[0.8528325008],"iteration":442,"passed_time":33.84467029,"remaining_time":42.55413398},
{"learn":[0.8526364845],"iteration":443,"passed_time":33.92209493,"remaining_time":42.47901978},
{"learn":[0.8524063194],"iteration":444,"passed_time":34.00119209,"remaining_time":42.40598115},
{"learn":[0.8520734302],"iteration":445,"passed_time":34.0848828,"remaining_time":42.33862124},
{"learn":[0.8517128395],"iteration":446,"passed_time":34.17377542,"remaining_time":42.27762373},
{"learn":[0.8513734242],"iteration":447,"passed_time":34.26790139,"remaining_time":42.22294992},
{"learn":[0.8512219018],"iteration":448,"passed_time":34.35330621,"remaining_time":42.15739805},
{"learn":[0.851063914],"iteration":449,"passed_time":34.42409154,"remaining_time":42.07388966},
{"learn":[0.8507929605],"iteration":450,"passed_time":34.50880405,"remaining_time":42.00739118},
{"learn":[0.850411257],"iteration":451,"passed_time":34.58555032,"remaining_time":41.93115393},
{"learn":[0.8501673681],"iteration":452,"passed_time":34.67236548,"remaining_time":41.86707267},
{"learn":[0.8498998945],"iteration":453,"passed_time":34.7695756,"remaining_time":41.81539269},
{"learn":[0.8495685676],"iteration":454,"passed_time":34.85531372,"remaining_time":41.74977137},
{"learn":[0.8493249071],"iteration":455,"passed_time":34.93418867,"remaining_time":41.6758742},
{"learn":[0.8490495533],"iteration":456,"passed_time":35.01122847,"remaining_time":41.59977475},
{"learn":[0.8487566286],"iteration":457,"passed_time":35.08974924,"remaining_time":41.52542378},
{"learn":[0.8485039862],"iteration":458,"passed_time":35.16371805,"remaining_time":41.44568947},
{"learn":[0.8481313767],"iteration":459,"passed_time":35.24558023,"remaining_time":41.37524636},
{"learn":[0.8479360075],"iteration":460,"passed_time":35.32123209,"remaining_time":41.29749262},
{"learn":[0.8477296447],"iteration":461,"passed_time":35.39083434,"remaining_time":41.21270319},
{"learn":[0.8473505348],"iteration":462,"passed_time":35.47034603,"remaining_time":41.13947261},
{"learn":[0.8470224578],"iteration":463,"passed_time":35.56458796,"remaining_time":41.08323092},
{"learn":[0.8468396528],"iteration":464,"passed_time":35.65293325,"remaining_time":41.02004148},
{"learn":[0.8465795192],"iteration":465,"passed_time":35.74684429,"remaining_time":40.963122},
{"learn":[0.8462269675],"iteration":466,"passed_time":35.82888171,"remaining_time":40.8924924},
{"learn":[0.8458552737],"iteration":467,"passed_time":35.91000392,"remaining_time":40.82077369},
{"learn":[0.8456312339],"iteration":468,"passed_time":35.98366015,"remaining_time":40.74056191},
{"learn":[0.8453074963],"iteration":469,"passed_time":36.06990593,"remaining_time":40.67457477},
{"learn":[0.8449847724],"iteration":470,"passed_time":36.14595958,"remaining_time":40.59705439},
{"learn":[0.8447381069],"iteration":471,"passed_time":36.22465872,"remaining_time":40.52249959},
{"learn":[0.8444013135],"iteration":472,"passed_time":36.30489183,"remaining_time":40.44963635},
{"learn":[0.8441196544],"iteration":473,"passed_time":36.38513143,"remaining_time":40.37674922},
{"learn":[0.8437815179],"iteration":474,"passed_time":36.47259903,"remaining_time":40.31181998},
{"learn":[0.8434567751],"iteration":475,"passed_time":36.55037455,"remaining_time":40.23612661},
{"learn":[0.843225191],"iteration":476,"passed_time":36.62762975,"remaining_time":40.159854},
{"learn":[0.8428078368],"iteration":477,"passed_time":36.73296306,"remaining_time":40.11423999},
{"learn":[0.8426227681],"iteration":478,"passed_time":36.83947175,"remaining_time":40.06965508},
{"learn":[0.8422725701],"iteration":479,"passed_time":36.94551781,"remaining_time":40.02431096},
{"learn":[0.8419219896],"iteration":480,"passed_time":37.05138428,"remaining_time":39.97852066},
{"learn":[0.8417228562],"iteration":481,"passed_time":37.13540684,"remaining_time":39.9090057},
{"learn":[0.8414121812],"iteration":482,"passed_time":37.2122242,"remaining_time":39.83171824},
{"learn":[0.8410817282],"iteration":483,"passed_time":37.30053663,"remaining_time":39.76668781},
{"learn":[0.8408138342],"iteration":484,"passed_time":37.38162835,"remaining_time":39.69389402},
{"learn":[0.840577641],"iteration":485,"passed_time":37.46793047,"remaining_time":39.62657667},
{"learn":[0.8404163552],"iteration":486,"passed_time":37.54237872,"remaining_time":39.54669462},
{"learn":[0.8401699421],"iteration":487,"passed_time":37.62618031,"remaining_time":39.4766482},
{"learn":[0.8400191704],"iteration":488,"passed_time":37.70096481,"remaining_time":39.39712273},
{"learn":[0.8398332853],"iteration":489,"passed_time":37.78559993,"remaining_time":39.32786931},
{"learn":[0.8396227441],"iteration":490,"passed_time":37.8591467,"remaining_time":39.24705839},
{"learn":[0.8394630322],"iteration":491,"passed_time":37.92576455,"remaining_time":39.15912274},
{"learn":[0.8392204492],"iteration":492,"passed_time":38.00227537,"remaining_time":39.08144749},
{"learn":[0.8389841269],"iteration":493,"passed_time":38.07979982,"remaining_time":39.0048152},
{"learn":[0.8387578352],"iteration":494,"passed_time":38.15501098,"remaining_time":38.92581928},
{"learn":[0.8385645911],"iteration":495,"passed_time":38.22373156,"remaining_time":38.84024336},
{"learn":[0.8382177962],"iteration":496,"passed_time":38.29454192,"remaining_time":38.75685027},
{"learn":[0.8379293566],"iteration":497,"passed_time":38.37082634,"remaining_time":38.67902575},
{"learn":[0.837467622],"iteration":498,"passed_time":38.45521449,"remaining_time":38.6093436},
{"learn":[0.8372388253],"iteration":499,"passed_time":38.52789734,"remaining_time":38.52789734},
{"learn":[0.8369340512],"iteration":500,"passed_time":38.60324912,"remaining_time":38.44914433},
{"learn":[0.83668854],"iteration":501,"passed_time":38.68031331,"remaining_time":38.37210364},
{"learn":[0.8364145479],"iteration":502,"passed_time":38.75671252,"remaining_time":38.29440581},
{"learn":[0.8360921193],"iteration":503,"passed_time":38.84791975,"remaining_time":38.23128611},
{"learn":[0.8359348184],"iteration":504,"passed_time":38.92730111,"remaining_time":38.15646346},
{"learn":[0.8356520481],"iteration":505,"passed_time":39.00182032,"remaining_time":38.07687597},
{"learn":[0.8354313959],"iteration":506,"passed_time":39.08142811,"remaining_time":38.00225652},
{"learn":[0.8351653153],"iteration":507,"passed_time":39.1629291,"remaining_time":37.92945102},
{"learn":[0.8348247727],"iteration":508,"passed_time":39.24434868,"remaining_time":37.85653282},
{"learn":[0.8345585971],"iteration":509,"passed_time":39.31593649,"remaining_time":37.77413506},
{"learn":[0.8342180158],"iteration":510,"passed_time":39.39262886,"remaining_time":37.69666441},
{"learn":[0.8339126725],"iteration":511,"passed_time":39.46955444,"remaining_time":37.61941907},
{"learn":[0.8335865353],"iteration":512,"passed_time":39.54763524,"remaining_time":37.54327166},
{"learn":[0.8333417786],"iteration":513,"passed_time":39.6274459,"remaining_time":37.46875235},
{"learn":[0.8330084091],"iteration":514,"passed_time":39.70821478,"remaining_time":37.39511489},
{"learn":[0.8327252701],"iteration":515,"passed_time":39.80027001,"remaining_time":37.33203621},
{"learn":[0.8326138944],"iteration":516,"passed_time":39.90019159,"remaining_time":37.27619446},
{"learn":[0.8322369387],"iteration":517,"passed_time":40.00769843,"remaining_time":37.22724063},
{"learn":[0.8319547229],"iteration":518,"passed_time":40.09675979,"remaining_time":37.1609662},
{"learn":[0.8318118881],"iteration":519,"passed_time":40.18448132,"remaining_time":37.09336737},
{"learn":[0.831537814],"iteration":520,"passed_time":40.27485488,"remaining_time":37.02812954},
{"learn":[0.8311038348],"iteration":521,"passed_time":40.35881006,"remaining_time":36.95691803},
{"learn":[0.8308263655],"iteration":522,"passed_time":40.44123259,"remaining_time":36.88425994},
{"learn":[0.8305812917],"iteration":523,"passed_time":40.51425603,"remaining_time":36.80302647},
{"learn":[0.8302262123],"iteration":524,"passed_time":40.60468781,"remaining_time":36.73757468},
{"learn":[0.8300677894],"iteration":525,"passed_time":40.71435181,"remaining_time":36.68935885},
{"learn":[0.8296698286],"iteration":526,"passed_time":40.84243433,"remaining_time":36.65744106},
{"learn":[0.8294288546],"iteration":527,"passed_time":40.95565156,"remaining_time":36.61187034},
{"learn":[0.8292471539],"iteration":528,"passed_time":41.05652765,"remaining_time":36.55505581},
{"learn":[0.8290065491],"iteration":529,"passed_time":41.18463691,"remaining_time":36.52222518},
{"learn":[0.8286836905],"iteration":530,"passed_time":41.28507156,"remaining_time":36.4645924},
{"learn":[0.8285016689],"iteration":531,"passed_time":41.37981711,"remaining_time":36.401794},
{"learn":[0.8282187639],"iteration":532,"passed_time":41.48127395,"remaining_time":36.34475598},
{"learn":[0.827993162],"iteration":533,"passed_time":41.58844592,"remaining_time":36.29253895},
{"learn":[0.8277796176],"iteration":534,"passed_time":41.68162693,"remaining_time":36.22795612},
{"learn":[0.8274064735],"iteration":535,"passed_time":41.75814973,"remaining_time":36.14884603},
{"learn":[0.8272667358],"iteration":536,"passed_time":41.8363966,"remaining_time":36.07123208},
{"learn":[0.8270490187],"iteration":537,"passed_time":41.91362472,"remaining_time":35.99274093},
{"learn":[0.8267070578],"iteration":538,"passed_time":41.99960908,"remaining_time":35.92174357},
{"learn":[0.8264133513],"iteration":539,"passed_time":42.08895792,"remaining_time":35.85355675},
{"learn":[0.8259255717],"iteration":540,"passed_time":42.17833259,"remaining_time":35.78531361},
{"learn":[0.8257014636],"iteration":541,"passed_time":42.27256653,"remaining_time":35.72109865},
{"learn":[0.8254421698],"iteration":542,"passed_time":42.3573251,"remaining_time":35.64879848},
{"learn":[0.8251404546],"iteration":543,"passed_time":42.44271052,"remaining_time":35.57697794},
{"learn":[0.8249438866],"iteration":544,"passed_time":42.53202307,"remaining_time":35.50838623},
{"learn":[0.8247178724],"iteration":545,"passed_time":42.62230194,"remaining_time":35.44052212},
{"learn":[0.8243543811],"iteration":546,"passed_time":42.71050997,"remaining_time":35.37086109},
{"learn":[0.8241582213],"iteration":547,"passed_time":42.78435485,"remaining_time":35.28928538},
{"learn":[0.8237522602],"iteration":548,"passed_time":42.87134099,"remaining_time":35.21853331},
{"learn":[0.8234018934],"iteration":549,"passed_time":42.94624819,"remaining_time":35.13783943},
{"learn":[0.8231522935],"iteration":550,"passed_time":43.02483043,"remaining_time":35.06016128},
{"learn":[0.8228202147],"iteration":551,"passed_time":43.1021206,"remaining_time":34.98143121},
{"learn":[0.8225839296],"iteration":552,"passed_time":43.18876007,"remaining_time":34.91026356},
{"learn":[0.8222670337],"iteration":553,"passed_time":43.26803463,"remaining_time":34.83311091},
{"learn":[0.8220944932],"iteration":554,"passed_time":43.3489267,"remaining_time":34.75724754},
{"learn":[0.8218770968],"iteration":555,"passed_time":43.42773186,"remaining_time":34.67969954},
{"learn":[0.8215878872],"iteration":556,"passed_time":43.50358983,"remaining_time":34.59980304},
{"learn":[0.8213302922],"iteration":557,"passed_time":43.57835788,"remaining_time":34.51905767},
{"learn":[0.8210414502],"iteration":558,"passed_time":43.65868252,"remaining_time":34.44271734},
{"learn":[0.8208701989],"iteration":559,"passed_time":43.74488331,"remaining_time":34.37097975},
{"learn":[0.8206061475],"iteration":560,"passed_time":43.8220489,"remaining_time":34.29212027},
{"learn":[0.8202299193],"iteration":561,"passed_time":43.91206554,"remaining_time":34.22328239},
{"learn":[0.8199987547],"iteration":562,"passed_time":43.99497345,"remaining_time":34.14885151},
{"learn":[0.8197888631],"iteration":563,"passed_time":44.08629368,"remaining_time":34.0808937},
{"learn":[0.8196171192],"iteration":564,"passed_time":44.16251541,"remaining_time":34.00122868},
{"learn":[0.8192485577],"iteration":565,"passed_time":44.27249191,"remaining_time":33.94745846},
{"learn":[0.8188847034],"iteration":566,"passed_time":44.38097148,"remaining_time":33.89234683},
{"learn":[0.8186980867],"iteration":567,"passed_time":44.49302195,"remaining_time":33.83976318},
{"learn":[0.8182962261],"iteration":568,"passed_time":44.6111983,"remaining_time":33.79161066},
{"learn":[0.8181618138],"iteration":569,"passed_time":44.72241613,"remaining_time":33.73796305},
{"learn":[0.8177580909],"iteration":570,"passed_time":44.80937236,"remaining_time":33.66588571},
{"learn":[0.8175012042],"iteration":571,"passed_time":44.8928178,"remaining_time":33.59112941},
{"learn":[0.8173592597],"iteration":572,"passed_time":44.96031571,"remaining_time":33.50445866},
{"learn":[0.8171229866],"iteration":573,"passed_time":45.02966877,"remaining_time":33.41923153},
{"learn":[0.8168109487],"iteration":574,"passed_time":45.10343514,"remaining_time":33.33732162},
{"learn":[0.8165146299],"iteration":575,"passed_time":45.18111075,"remaining_time":33.25831764},
{"learn":[0.8162021143],"iteration":576,"passed_time":45.26647127,"remaining_time":33.18495207},
{"learn":[0.8159373948],"iteration":577,"passed_time":45.3460723,"remaining_time":33.10733998},
{"learn":[0.8157324149],"iteration":578,"passed_time":45.42480318,"remaining_time":33.02908832},
{"learn":[0.8152604478],"iteration":579,"passed_time":45.50836335,"remaining_time":32.95433208},
{"learn":[0.8150196434],"iteration":580,"passed_time":45.59816968,"remaining_time":32.88405008},
{"learn":[0.8148342877],"iteration":581,"passed_time":45.67645761,"remaining_time":32.80542832},
{"learn":[0.8146159791],"iteration":582,"passed_time":45.75627066,"remaining_time":32.72789857},
{"learn":[0.8143141742],"iteration":583,"passed_time":45.83537225,"remaining_time":32.6498542},
{"learn":[0.8140639636],"iteration":584,"passed_time":45.91185578,"remaining_time":32.56994897},
{"learn":[0.8137317825],"iteration":585,"passed_time":45.98833082,"remaining_time":32.49004942},
{"learn":[0.8133990987],"iteration":586,"passed_time":46.06889021,"remaining_time":32.41303519},
{"learn":[0.8130645154],"iteration":587,"passed_time":46.15040456,"remaining_time":32.33667803},
{"learn":[0.8126688738],"iteration":588,"passed_time":46.23165389,"remaining_time":32.26011842},
{"learn":[0.8124846589],"iteration":589,"passed_time":46.30467506,"remaining_time":32.17782504},
{"learn":[0.8122893361],"iteration":590,"passed_time":46.37941426,"remaining_time":32.096752},
{"learn":[0.8119979749],"iteration":591,"passed_time":46.45819458,"remaining_time":32.01848545},
{"learn":[0.811792423],"iteration":592,"passed_time":46.5332614,"remaining_time":31.93766845},
{"learn":[0.8114991196],"iteration":593,"passed_time":46.60864715,"remaining_time":31.85708879},
{"learn":[0.8112238698],"iteration":594,"passed_time":46.69367291,"remaining_time":31.78308828},
{"learn":[0.8109266869],"iteration":595,"passed_time":46.77547237,"remaining_time":31.70686382},
{"learn":[0.8104001783],"iteration":596,"passed_time":46.8561985,"remaining_time":31.62989614},
{"learn":[0.8101347344],"iteration":597,"passed_time":46.93579683,"remaining_time":31.55215773},
{"learn":[0.8098481152],"iteration":598,"passed_time":47.01373202,"remaining_time":31.47329973},
{"learn":[0.8095265845],"iteration":599,"passed_time":47.08905525,"remaining_time":31.3927035},
{"learn":[0.8091885892],"iteration":600,"passed_time":47.16764183,"remaining_time":31.31429133},
{"learn":[0.8089460028],"iteration":601,"passed_time":47.23825522,"remaining_time":31.23060727},
{"learn":[0.8086992019],"iteration":602,"passed_time":47.31404006,"remaining_time":31.15037132},
{"learn":[0.8084394632],"iteration":603,"passed_time":47.38665487,"remaining_time":31.06807174},
{"learn":[0.8083161451],"iteration":604,"passed_time":47.46052638,"remaining_time":30.98662466},
{"learn":[0.8081086167],"iteration":605,"passed_time":47.53427557,"remaining_time":30.90512306},
{"learn":[0.8078977288],"iteration":606,"passed_time":47.60931412,"remaining_time":30.82448179},
{"learn":[0.8076952394],"iteration":607,"passed_time":47.70647388,"remaining_time":30.75812132},
{"learn":[0.8074810774],"iteration":608,"passed_time":47.78908946,"remaining_time":30.6823218},
{"learn":[0.8071868658],"iteration":609,"passed_time":47.87126989,"remaining_time":30.60622173},
{"learn":[0.8068328305],"iteration":610,"passed_time":47.94946937,"remaining_time":30.52756724},
{"learn":[0.8064457095],"iteration":611,"passed_time":48.03666969,"remaining_time":30.45462066},
{"learn":[0.8061302144],"iteration":612,"passed_time":48.11996772,"remaining_time":30.37916396},
{"learn":[0.8058915524],"iteration":613,"passed_time":48.19043218,"remaining_time":30.29561372},
{"learn":[0.8057202159],"iteration":614,"passed_time":48.25467074,"remaining_time":30.20820851},
{"learn":[0.8055386276],"iteration":615,"passed_time":48.33302664,"remaining_time":30.12967895},
{"learn":[0.8051838625],"iteration":616,"passed_time":48.40852798,"remaining_time":30.04937798},
{"learn":[0.8048306387],"iteration":617,"passed_time":48.49171767,"remaining_time":29.9738449},
{"learn":[0.8045873999],"iteration":618,"passed_time":48.57184833,"remaining_time":29.89640422},
{"learn":[0.8044461574],"iteration":619,"passed_time":48.65170439,"remaining_time":29.81878656},
{"learn":[0.8041350609],"iteration":620,"passed_time":48.72702913,"remaining_time":29.7383962},
{"learn":[0.8038653403],"iteration":621,"passed_time":48.8059996,"remaining_time":29.6602377},
{"learn":[0.8036423653],"iteration":622,"passed_time":48.88611142,"remaining_time":29.58276727},
{"learn":[0.8034275767],"iteration":623,"passed_time":48.96284836,"remaining_time":29.50325478},
{"learn":[0.8031682745],"iteration":624,"passed_time":49.04107572,"remaining_time":29.42464543},
{"learn":[0.8030155349],"iteration":625,"passed_time":49.11913266,"remaining_time":29.34593549},
{"learn":[0.802751668],"iteration":626,"passed_time":49.19836903,"remaining_time":29.26792927},
{"learn":[0.8025836202],"iteration":627,"passed_time":49.30896376,"remaining_time":29.20849446},
{"learn":[0.8022407828],"iteration":628,"passed_time":49.3977882,"remaining_time":29.13605632},
{"learn":[0.8020164105],"iteration":629,"passed_time":49.48538236,"remaining_time":29.06284361},
{"learn":[0.8017639506],"iteration":630,"passed_time":49.56951065,"remaining_time":28.98755852},
{"learn":[0.8015293298],"iteration":631,"passed_time":49.66301481,"remaining_time":28.91770482},
{"learn":[0.8011487954],"iteration":632,"passed_time":49.7905005,"remaining_time":28.86747817},
{"learn":[0.8008739987],"iteration":633,"passed_time":49.92997679,"remaining_time":28.82392982},
{"learn":[0.8007321719],"iteration":634,"passed_time":50.0106504,"remaining_time":28.74627936},
{"learn":[0.8004014437],"iteration":635,"passed_time":50.12365288,"remaining_time":28.68712209},
{"learn":[0.8002205994],"iteration":636,"passed_time":50.21554328,"remaining_time":28.61576485},
{"learn":[0.7999699599],"iteration":637,"passed_time":50.3227095,"remaining_time":28.55301072},
{"learn":[0.7996748486],"iteration":638,"passed_time":50.41113306,"remaining_time":28.47952901},
{"learn":[0.7994264768],"iteration":639,"passed_time":50.48699784,"remaining_time":28.39893628},
{"learn":[0.799237326],"iteration":640,"passed_time":50.56040329,"remaining_time":28.31698094},
{"learn":[0.7989811248],"iteration":641,"passed_time":50.63529362,"remaining_time":28.23588024},
{"learn":[0.7987899523],"iteration":642,"passed_time":50.71811752,"remaining_time":28.15920366},
{"learn":[0.798466935],"iteration":643,"passed_time":50.79654916,"remaining_time":28.08007997},
{"learn":[0.7981857443],"iteration":644,"passed_time":50.87783898,"remaining_time":28.00253153},
{"learn":[0.7978697574],"iteration":645,"passed_time":50.96775535,"remaining_time":27.92969875},
{"learn":[0.7975036875],"iteration":646,"passed_time":51.04942678,"remaining_time":27.85231477},
{"learn":[0.7973005293],"iteration":647,"passed_time":51.14084262,"remaining_time":27.7802108},
{"learn":[0.7970577659],"iteration":648,"passed_time":51.22484535,"remaining_time":27.70403809},
{"learn":[0.7968202266],"iteration":649,"passed_time":51.31086627,"remaining_time":27.62892799},
{"learn":[0.7965720655],"iteration":650,"passed_time":51.39425589,"remaining_time":27.55237374},
{"learn":[0.7964112197],"iteration":651,"passed_time":51.47963108,"remaining_time":27.47685831},
{"learn":[0.7961284912],"iteration":652,"passed_time":51.56514475,"remaining_time":27.40138626},
{"learn":[0.7958844789],"iteration":653,"passed_time":51.67064012,"remaining_time":27.33645487},
{"learn":[0.7955547171],"iteration":654,"passed_time":51.76584065,"remaining_time":27.26597714},
{"learn":[0.7952412851],"iteration":655,"passed_time":51.85332458,"remaining_time":27.19137752},
{"learn":[0.7950762864],"iteration":656,"passed_time":51.92953463,"remaining_time":27.11085293},
{"learn":[0.7948106627],"iteration":657,"passed_time":52.02085649,"remaining_time":27.03819593},
{"learn":[0.7945577908],"iteration":658,"passed_time":52.11360462,"remaining_time":26.9662203},
{"learn":[0.7943368434],"iteration":659,"passed_time":52.21121684,"remaining_time":26.89668747},
{"learn":[0.7941404241],"iteration":660,"passed_time":52.29409945,"remaining_time":26.81951545},
{"learn":[0.7938364186],"iteration":661,"passed_time":52.39440688,"remaining_time":26.75122285},
{"learn":[0.7935596563],"iteration":662,"passed_time":52.50532449,"remaining_time":26.68822678},
{"learn":[0.7934218779],"iteration":663,"passed_time":52.59284496,"remaining_time":26.61324685},
{"learn":[0.7930615325],"iteration":664,"passed_time":52.68260412,"remaining_time":26.53935696},
{"learn":[0.7928990121],"iteration":665,"passed_time":52.75676193,"remaining_time":26.45759532},
{"learn":[0.7927310037],"iteration":666,"passed_time":52.84769404,"remaining_time":26.38423106},
{"learn":[0.7925409894],"iteration":667,"passed_time":52.93380894,"remaining_time":26.30842001},
{"learn":[0.7923155425],"iteration":668,"passed_time":53.02660805,"remaining_time":26.2358853},
{"learn":[0.7921128979],"iteration":669,"passed_time":53.13154117,"remaining_time":26.16926655},
{"learn":[0.7919726519],"iteration":670,"passed_time":53.2410599,"remaining_time":26.10478198},
{"learn":[0.7916696544],"iteration":671,"passed_time":53.35307163,"remaining_time":26.0413802},
{"learn":[0.7915350191],"iteration":672,"passed_time":53.4464974,"remaining_time":25.96880334},
{"learn":[0.7912246597],"iteration":673,"passed_time":53.549113,"remaining_time":25.90060955},
{"learn":[0.7910175072],"iteration":674,"passed_time":53.63892229,"remaining_time":25.82614777},
{"learn":[0.7908437735],"iteration":675,"passed_time":53.73165418,"remaining_time":25.75304135},
{"learn":[0.7905058087],"iteration":676,"passed_time":53.81832849,"remaining_time":25.67698686},
{"learn":[0.7902921758],"iteration":677,"passed_time":53.89700727,"remaining_time":25.59710375},
{"learn":[0.7901214574],"iteration":678,"passed_time":53.97697735,"remaining_time":25.51783465},
{"learn":[0.7898283493],"iteration":679,"passed_time":54.0981398,"remaining_time":25.45794814},
{"learn":[0.7895342837],"iteration":680,"passed_time":54.2048168,"remaining_time":25.39109627},
{"learn":[0.7893467714],"iteration":681,"passed_time":54.28859515,"remaining_time":25.31345052},
{"learn":[0.7891009949],"iteration":682,"passed_time":54.36905164,"remaining_time":25.23424505},
{"learn":[0.7887751744],"iteration":683,"passed_time":54.44697464,"remaining_time":25.15386547},
{"learn":[0.7884760953],"iteration":684,"passed_time":54.52599713,"remaining_time":25.07399868},
{"learn":[0.7881183752],"iteration":685,"passed_time":54.62179984,"remaining_time":25.00181509},
{"learn":[0.7878203518],"iteration":686,"passed_time":54.71433854,"remaining_time":24.92807564},
{"learn":[0.787590219],"iteration":687,"passed_time":54.81265255,"remaining_time":24.85690057},
{"learn":[0.7873999813],"iteration":688,"passed_time":54.90785318,"remaining_time":24.78424142},
{"learn":[0.7871636216],"iteration":689,"passed_time":54.99115608,"remaining_time":24.70617157},
{"learn":[0.7869154616],"iteration":690,"passed_time":55.07549812,"remaining_time":24.62855126},
{"learn":[0.7865722573],"iteration":691,"passed_time":55.17073895,"remaining_time":24.55576242},
{"learn":[0.7862913549],"iteration":692,"passed_time":55.26026982,"remaining_time":24.48037927},
{"learn":[0.7859637077],"iteration":693,"passed_time":55.3446087,"remaining_time":24.40266608},
{"learn":[0.7856208214],"iteration":694,"passed_time":55.44720642,"remaining_time":24.3329467},
{"learn":[0.7853729113],"iteration":695,"passed_time":55.5310383,"remaining_time":24.25493627},
{"learn":[0.7851187791],"iteration":696,"passed_time":55.61477114,"remaining_time":24.17686608},
{"learn":[0.78490213],"iteration":697,"passed_time":55.70782835,"remaining_time":24.10281398},
{"learn":[0.78463918],"iteration":698,"passed_time":55.79244639,"remaining_time":24.02507348},
{"learn":[0.7843891866],"iteration":699,"passed_time":55.87342495,"remaining_time":23.94575355},
{"learn":[0.7841986632],"iteration":700,"passed_time":55.95473348,"remaining_time":23.86656963},
{"learn":[0.7839792616],"iteration":701,"passed_time":56.03477359,"remaining_time":23.78684121},
{"learn":[0.7837872943],"iteration":702,"passed_time":56.11017988,"remaining_time":23.70515423},
{"learn":[0.7835348972],"iteration":703,"passed_time":56.19402874,"remaining_time":23.62703481},
{"learn":[0.7832355854],"iteration":704,"passed_time":56.28665904,"remaining_time":23.55257364},
{"learn":[0.7828666841],"iteration":705,"passed_time":56.37061401,"remaining_time":23.47444833},
{"learn":[0.782531797],"iteration":706,"passed_time":56.45439985,"remaining_time":23.39623643},
{"learn":[0.7822692812],"iteration":707,"passed_time":56.53426992,"remaining_time":23.31639381},
{"learn":[0.7818945306],"iteration":708,"passed_time":56.61787165,"remaining_time":23.23808272},
{"learn":[0.7816070991],"iteration":709,"passed_time":56.69788087,"remaining_time":23.15828937},
{"learn":[0.7812644595],"iteration":710,"passed_time":56.78463327,"remaining_time":23.08123631},
{"learn":[0.7809393561],"iteration":711,"passed_time":56.85542002,"remaining_time":22.99769798},
{"learn":[0.7807644108],"iteration":712,"passed_time":56.93849116,"remaining_time":22.9191402},
{"learn":[0.7805221224],"iteration":713,"passed_time":57.01427423,"remaining_time":22.83765046},
{"learn":[0.7803889926],"iteration":714,"passed_time":57.09292582,"remaining_time":22.75732008},
{"learn":[0.7801456216],"iteration":715,"passed_time":57.16764447,"remaining_time":22.6754344},
{"learn":[0.7798966445],"iteration":716,"passed_time":57.24526521,"remaining_time":22.59471416},
{"learn":[0.7796294893],"iteration":717,"passed_time":57.32524197,"remaining_time":22.51492791},
{"learn":[0.7793887003],"iteration":718,"passed_time":57.40966413,"remaining_time":22.43687847},
{"learn":[0.7790925209],"iteration":719,"passed_time":57.49309945,"remaining_time":22.35842756},
{"learn":[0.7789099831],"iteration":720,"passed_time":57.57963145,"remaining_time":22.28116113},
{"learn":[0.778607287],"iteration":721,"passed_time":57.65746286,"remaining_time":22.20051894},
{"learn":[0.7782986641],"iteration":722,"passed_time":57.75259591,"remaining_time":22.12651323},
{"learn":[0.7778678071],"iteration":723,"passed_time":57.85607891,"remaining_time":22.05563229},
{"learn":[0.7776130631],"iteration":724,"passed_time":57.93073534,"remaining_time":21.9737272},
{"learn":[0.777233589],"iteration":725,"passed_time":58.021408,"remaining_time":21.89788677},
{"learn":[0.7769348961],"iteration":726,"passed_time":58.11555142,"remaining_time":21.82330885},
{"learn":[0.7767992043],"iteration":727,"passed_time":58.20479098,"remaining_time":21.74684498},
{"learn":[0.7765764014],"iteration":728,"passed_time":58.29843054,"remaining_time":21.67198172},
{"learn":[0.7762704297],"iteration":729,"passed_time":58.38733755,"remaining_time":21.59531663},
{"learn":[0.7760591563],"iteration":730,"passed_time":58.46366841,"remaining_time":21.51399015},
{"learn":[0.7757427181],"iteration":731,"passed_time":58.54780861,"remaining_time":21.43553649},
{"learn":[0.7755154983],"iteration":732,"passed_time":58.64824493,"remaining_time":21.36300327},
{"learn":[0.7751976841],"iteration":733,"passed_time":58.74985317,"remaining_time":21.29081872},
{"learn":[0.7749594445],"iteration":734,"passed_time":58.8417118,"remaining_time":21.21503895},
{"learn":[0.7747334455],"iteration":735,"passed_time":58.92420833,"remaining_time":21.13585734},
{"learn":[0.7745033279],"iteration":736,"passed_time":59.0077337,"remaining_time":21.05703387},
{"learn":[0.7744113507],"iteration":737,"passed_time":59.0871192,"remaining_time":20.97672795},
{"learn":[0.7741871353],"iteration":738,"passed_time":59.17198605,"remaining_time":20.89836043},
{"learn":[0.7738158038],"iteration":739,"passed_time":59.25861991,"remaining_time":20.82059618},
{"learn":[0.7735218102],"iteration":740,"passed_time":59.33668797,"remaining_time":20.73981401},
{"learn":[0.7733350198],"iteration":741,"passed_time":59.42252926,"remaining_time":20.66174198},
{"learn":[0.7730467893],"iteration":742,"passed_time":59.51321549,"remaining_time":20.58532487},
{"learn":[0.7727843712],"iteration":743,"passed_time":59.58953959,"remaining_time":20.5039276},
{"learn":[0.7725603766],"iteration":744,"passed_time":59.67753191,"remaining_time":20.42653777},
{"learn":[0.7722552031],"iteration":745,"passed_time":59.77199833,"remaining_time":20.35132383},
{"learn":[0.7721020023],"iteration":746,"passed_time":59.84600242,"remaining_time":20.269128},
{"learn":[0.7718760303],"iteration":747,"passed_time":59.9310612,"remaining_time":20.19067837},
{"learn":[0.7716640742],"iteration":748,"passed_time":60.02414137,"remaining_time":20.11489918},
{"learn":[0.7714726732],"iteration":749,"passed_time":60.11372141,"remaining_time":20.03790714},
{"learn":[0.7712443062],"iteration":750,"passed_time":60.20977768,"remaining_time":19.96302882},
{"learn":[0.7709250702],"iteration":751,"passed_time":60.30359906,"remaining_time":19.88735714},
{"learn":[0.7708287199],"iteration":752,"passed_time":60.38475771,"remaining_time":19.80748361},
{"learn":[0.7704764602],"iteration":753,"passed_time":60.48817878,"remaining_time":19.73487},
{"learn":[0.7702216442],"iteration":754,"passed_time":60.57880281,"remaining_time":19.6580221},
{"learn":[0.7698722783],"iteration":755,"passed_time":60.67294619,"remaining_time":19.58227364},
{"learn":[0.7696053439],"iteration":756,"passed_time":60.77100383,"remaining_time":19.50773307},
{"learn":[0.7692917439],"iteration":757,"passed_time":60.87030511,"remaining_time":19.43352749},
{"learn":[0.7690974672],"iteration":758,"passed_time":60.95612092,"remaining_time":19.35497384},
{"learn":[0.7688910213],"iteration":759,"passed_time":61.03347245,"remaining_time":19.27372814},
{"learn":[0.768678167],"iteration":760,"passed_time":61.1204633,"remaining_time":19.19552001},
{"learn":[0.7685166618],"iteration":761,"passed_time":61.20656688,"remaining_time":19.1170117},
{"learn":[0.7683288308],"iteration":762,"passed_time":61.29013553,"remaining_time":19.03769609},
{"learn":[0.7680907279],"iteration":763,"passed_time":61.37696528,"remaining_time":18.95937671},
{"learn":[0.7678247921],"iteration":764,"passed_time":61.46143394,"remaining_time":18.88030977},
{"learn":[0.7675549372],"iteration":765,"passed_time":61.54547356,"remaining_time":18.80109767},
{"learn":[0.7672148969],"iteration":766,"passed_time":61.64055965,"remaining_time":18.72522868},
{"learn":[0.7668449151],"iteration":767,"passed_time":61.73726435,"remaining_time":18.64979861},
{"learn":[0.7666986447],"iteration":768,"passed_time":61.82253299,"remaining_time":18.57087792},
{"learn":[0.7664045792],"iteration":769,"passed_time":61.91595331,"remaining_time":18.49437567},
{"learn":[0.7661250001],"iteration":770,"passed_time":62.00156472,"remaining_time":18.41551015},
{"learn":[0.765721682],"iteration":771,"passed_time":62.09810339,"remaining_time":18.33985437},
{"learn":[0.7654956962],"iteration":772,"passed_time":62.1749279,"remaining_time":18.25835528},
{"learn":[0.7652807986],"iteration":773,"passed_time":62.25991931,"remaining_time":18.17925293},
{"learn":[0.765018302],"iteration":774,"passed_time":62.35866994,"remaining_time":18.10412998},
{"learn":[0.7648349251],"iteration":775,"passed_time":62.44048588,"remaining_time":18.02405778},
{"learn":[0.7646414128],"iteration":776,"passed_time":62.53364783,"remaining_time":17.94723741},
{"learn":[0.7645039071],"iteration":777,"passed_time":62.61807847,"remaining_time":17.86788357},
{"learn":[0.7642169779],"iteration":778,"passed_time":62.71146673,"remaining_time":17.79105795},
{"learn":[0.764033742],"iteration":779,"passed_time":62.79277454,"remaining_time":17.71078256},
{"learn":[0.7638053633],"iteration":780,"passed_time":62.875501,"remaining_time":17.63090233},
{"learn":[0.7634977003],"iteration":781,"passed_time":62.96955049,"remaining_time":17.55417136},
{"learn":[0.7632854683],"iteration":782,"passed_time":63.05325171,"remaining_time":17.47452825},
{"learn":[0.762977474],"iteration":783,"passed_time":63.14878841,"remaining_time":17.39813558},
{"learn":[0.7627666108],"iteration":784,"passed_time":63.25350561,"remaining_time":17.32420854},
{"learn":[0.7625773452],"iteration":785,"passed_time":63.36136774,"remaining_time":17.25105941},
{"learn":[0.7623152323],"iteration":786,"passed_time":63.45515655,"remaining_time":17.17401315},
{"learn":[0.7621453218],"iteration":787,"passed_time":63.53443597,"remaining_time":17.09302084},
{"learn":[0.7618403955],"iteration":788,"passed_time":63.61672215,"remaining_time":17.01283698},
{"learn":[0.7616920858],"iteration":789,"passed_time":63.70522433,"remaining_time":16.93430014},
{"learn":[0.7614967717],"iteration":790,"passed_time":63.79004523,"remaining_time":16.85476543},
{"learn":[0.7612456229],"iteration":791,"passed_time":63.87171675,"remaining_time":16.77439026},
{"learn":[0.7611230083],"iteration":792,"passed_time":63.94033583,"remaining_time":16.69060469},
{"learn":[0.7607644017],"iteration":793,"passed_time":64.03138222,"remaining_time":16.61267599},
{"learn":[0.7605883315],"iteration":794,"passed_time":64.10886298,"remaining_time":16.53121624},
{"learn":[0.7603822198],"iteration":795,"passed_time":64.18885708,"remaining_time":16.45041061},
{"learn":[0.7601781716],"iteration":796,"passed_time":64.27029561,"remaining_time":16.36997492},
{"learn":[0.7599428433],"iteration":797,"passed_time":64.34898958,"remaining_time":16.28884197},
{"learn":[0.7597315878],"iteration":798,"passed_time":64.42640611,"remaining_time":16.20739378},
{"learn":[0.7596232811],"iteration":799,"passed_time":64.49887032,"remaining_time":16.12471758},
{"learn":[0.7593345888],"iteration":800,"passed_time":64.5758522,"remaining_time":16.04318925},
{"learn":[0.759063184],"iteration":801,"passed_time":64.66157724,"remaining_time":15.96383079},
{"learn":[0.7587611878],"iteration":802,"passed_time":64.74467778,"remaining_time":15.88381261},
{"learn":[0.7585053372],"iteration":803,"passed_time":64.83407264,"remaining_time":15.80532119},
{"learn":[0.7581425283],"iteration":804,"passed_time":64.92023816,"remaining_time":15.72602042},
{"learn":[0.7579771644],"iteration":805,"passed_time":64.99566288,"remaining_time":15.64411737},
{"learn":[0.7578274385],"iteration":806,"passed_time":65.06965138,"remaining_time":15.56188688},
{"learn":[0.7576375607],"iteration":807,"passed_time":65.14324235,"remaining_time":15.47958234},
{"learn":[0.7573613677],"iteration":808,"passed_time":65.22314725,"remaining_time":15.39879002},
{"learn":[0.7571790274],"iteration":809,"passed_time":65.30226503,"remaining_time":15.31781525},
{"learn":[0.7569354633],"iteration":810,"passed_time":65.3858702,"remaining_time":15.23789084},
{"learn":[0.7567194843],"iteration":811,"passed_time":65.45882438,"remaining_time":15.15549136},
{"learn":[0.7565865028],"iteration":812,"passed_time":65.52438356,"remaining_time":15.07141418},
{"learn":[0.7562461185],"iteration":813,"passed_time":65.61476906,"remaining_time":14.99305534},
{"learn":[0.7559220753],"iteration":814,"passed_time":65.69949263,"remaining_time":14.91338176},
{"learn":[0.7556580615],"iteration":815,"passed_time":65.77319086,"remaining_time":14.8312097},
{"learn":[0.7554456596],"iteration":816,"passed_time":65.85030448,"remaining_time":14.7498234},
{"learn":[0.7551453369],"iteration":817,"passed_time":65.93323233,"remaining_time":14.66974118},
{"learn":[0.7548429032],"iteration":818,"passed_time":66.02148363,"remaining_time":14.59082849},
{"learn":[0.7545345796],"iteration":819,"passed_time":66.10154724,"remaining_time":14.51009574},
{"learn":[0.7543662052],"iteration":820,"passed_time":66.17359262,"remaining_time":14.42761642},
{"learn":[0.7540926875],"iteration":821,"passed_time":66.24898763,"remaining_time":14.34588783},
{"learn":[0.7538034112],"iteration":822,"passed_time":66.33114447,"remaining_time":14.26562888},
{"learn":[0.7535848903],"iteration":823,"passed_time":66.41667839,"remaining_time":14.18608665},
{"learn":[0.7534035152],"iteration":824,"passed_time":66.49008061,"remaining_time":14.10395649},
{"learn":[0.7530955242],"iteration":825,"passed_time":66.57552943,"remaining_time":14.02438513},
{"learn":[0.7527363128],"iteration":826,"passed_time":66.66760242,"remaining_time":13.94618527},
{"learn":[0.7524904032],"iteration":827,"passed_time":66.76565379,"remaining_time":13.86919378},
{"learn":[0.7522275665],"iteration":828,"passed_time":66.84807773,"remaining_time":13.78892798},
{"learn":[0.7520066773],"iteration":829,"passed_time":66.92443972,"remaining_time":13.70741536},
{"learn":[0.7517560714],"iteration":830,"passed_time":67.00094991,"remaining_time":13.62594529},
{"learn":[0.7515117805],"iteration":831,"passed_time":67.08752075,"remaining_time":13.54651861},
{"learn":[0.7512269669],"iteration":832,"passed_time":67.16112011,"remaining_time":13.46447426},
{"learn":[0.7511198036],"iteration":833,"passed_time":67.238764,"remaining_time":13.38325518},
{"learn":[0.7508841804],"iteration":834,"passed_time":67.31163813,"remaining_time":13.30110214},
{"learn":[0.7506063319],"iteration":835,"passed_time":67.39031043,"remaining_time":13.22010874},
{"learn":[0.7502911181],"iteration":836,"passed_time":67.47215025,"remaining_time":13.13973774},
{"learn":[0.7500016357],"iteration":837,"passed_time":67.55010089,"remaining_time":13.05861139},
{"learn":[0.7497853551],"iteration":838,"passed_time":67.63819497,"remaining_time":12.97943908},
{"learn":[0.7495146554],"iteration":839,"passed_time":67.72436384,"remaining_time":12.89987883},
{"learn":[0.7493857169],"iteration":840,"passed_time":67.80730922,"remaining_time":12.81969342},
{"learn":[0.7490170649],"iteration":841,"passed_time":67.90482749,"remaining_time":12.74223604},
{"learn":[0.7487755057],"iteration":842,"passed_time":67.99459335,"remaining_time":12.66328726},
{"learn":[0.7486428902],"iteration":843,"passed_time":68.07717191,"remaining_time":12.58298438},
{"learn":[0.7483864895],"iteration":844,"passed_time":68.15906795,"remaining_time":12.50255093},
{"learn":[0.7480785565],"iteration":845,"passed_time":68.23859952,"remaining_time":12.4216836},
{"learn":[0.7479354806],"iteration":846,"passed_time":68.30957158,"remaining_time":12.33927326},
{"learn":[0.7476713551],"iteration":847,"passed_time":68.39001566,"remaining_time":12.25858771},
{"learn":[0.7472719495],"iteration":848,"passed_time":68.47448384,"remaining_time":12.17861845},
{"learn":[0.7470172534],"iteration":849,"passed_time":68.55689627,"remaining_time":12.09827581},
{"learn":[0.7467636357],"iteration":850,"passed_time":68.64284607,"remaining_time":12.01854767},
{"learn":[0.7464833494],"iteration":851,"passed_time":68.72432628,"remaining_time":11.93802851},
{"learn":[0.7462553569],"iteration":852,"passed_time":68.80605921,"remaining_time":11.85755065},
{"learn":[0.7460201101],"iteration":853,"passed_time":68.87940421,"remaining_time":11.77563585},
{"learn":[0.7457877123],"iteration":854,"passed_time":68.95807022,"remaining_time":11.69464349},
{"learn":[0.7456039864],"iteration":855,"passed_time":69.04109863,"remaining_time":11.61439042},
{"learn":[0.7453646906],"iteration":856,"passed_time":69.113578,"remaining_time":11.53237066},
{"learn":[0.7451033552],"iteration":857,"passed_time":69.18610156,"remaining_time":11.45038044},
{"learn":[0.7449179219],"iteration":858,"passed_time":69.26798598,"remaining_time":11.3699488},
{"learn":[0.74449375],"iteration":859,"passed_time":69.3568233,"remaining_time":11.29064565},
{"learn":[0.7443278096],"iteration":860,"passed_time":69.4294758,"remaining_time":11.20870748},
{"learn":[0.7438922735],"iteration":861,"passed_time":69.51670303,"remaining_time":11.12912415},
{"learn":[0.7436153884],"iteration":862,"passed_time":69.60005691,"remaining_time":11.04890822},
{"learn":[0.7434205599],"iteration":863,"passed_time":69.67343637,"remaining_time":10.96711498},
{"learn":[0.7432385746],"iteration":864,"passed_time":69.75834065,"remaining_time":10.88713987},
{"learn":[0.7430593741],"iteration":865,"passed_time":69.83022738,"remaining_time":10.80513911},
{"learn":[0.7428031228],"iteration":866,"passed_time":69.90973584,"remaining_time":10.72433087},
{"learn":[0.7425775763],"iteration":867,"passed_time":69.98319845,"remaining_time":10.64260622},
{"learn":[0.7424147407],"iteration":868,"passed_time":70.05983213,"remaining_time":10.56137861},
{"learn":[0.7422020264],"iteration":869,"passed_time":70.1390246,"remaining_time":10.48054391},
{"learn":[0.7419980953],"iteration":870,"passed_time":70.22232188,"remaining_time":10.40032092},
{"learn":[0.7418212764],"iteration":871,"passed_time":70.29880891,"remaining_time":10.31909122},
{"learn":[0.7414492304],"iteration":872,"passed_time":70.38813494,"remaining_time":10.23974014},
{"learn":[0.7411318945],"iteration":873,"passed_time":70.46442047,"remaining_time":10.15848625},
{"learn":[0.7407858807],"iteration":874,"passed_time":70.55011103,"remaining_time":10.07858729},
{"learn":[0.7405211633],"iteration":875,"passed_time":70.64052444,"remaining_time":9.999343643},
{"learn":[0.7401885653],"iteration":876,"passed_time":70.73229655,"remaining_time":9.92026508},
{"learn":[0.7398563771],"iteration":877,"passed_time":70.82231122,"remaining_time":9.840913404},
{"learn":[0.739509825],"iteration":878,"passed_time":70.91066298,"remaining_time":9.761308556},
{"learn":[0.7392200728],"iteration":879,"passed_time":71.00250522,"remaining_time":9.682159803},
{"learn":[0.7390135234],"iteration":880,"passed_time":71.07849297,"remaining_time":9.600840708},
{"learn":[0.7386977838],"iteration":881,"passed_time":71.1574652,"remaining_time":9.519932986},
{"learn":[0.7383674906],"iteration":882,"passed_time":71.23752034,"remaining_time":9.439173137},
{"learn":[0.7380521006],"iteration":883,"passed_time":71.31455744,"remaining_time":9.358018849},
{"learn":[0.7378542331],"iteration":884,"passed_time":71.3965514,"remaining_time":9.277517979},
{"learn":[0.7376499277],"iteration":885,"passed_time":71.47479966,"remaining_time":9.196531784},
{"learn":[0.7374533263],"iteration":886,"passed_time":71.55295701,"remaining_time":9.115540183},
{"learn":[0.7372616571],"iteration":887,"passed_time":71.62871512,"remaining_time":9.034252357},
{"learn":[0.7369655433],"iteration":888,"passed_time":71.70962627,"remaining_time":8.953620378},
{"learn":[0.7367731387],"iteration":889,"passed_time":71.78679737,"remaining_time":8.872525517},
{"learn":[0.7364772465],"iteration":890,"passed_time":71.87074877,"remaining_time":8.79226893},
{"learn":[0.7362464218],"iteration":891,"passed_time":71.94634472,"remaining_time":8.71099241},
{"learn":[0.7359811857],"iteration":892,"passed_time":72.020362,"remaining_time":8.629539456},
{"learn":[0.7358544963],"iteration":893,"passed_time":72.09723612,"remaining_time":8.548441867},
{"learn":[0.7354846659],"iteration":894,"passed_time":72.18144202,"remaining_time":8.468213868},
{"learn":[0.7353261195],"iteration":895,"passed_time":72.25787067,"remaining_time":8.387074275},
{"learn":[0.7351916354],"iteration":896,"passed_time":72.326355,"remaining_time":8.30503296},
{"learn":[0.7350313704],"iteration":897,"passed_time":72.39911745,"remaining_time":8.223507773},
{"learn":[0.7347805482],"iteration":898,"passed_time":72.47942302,"remaining_time":8.142849527},
{"learn":[0.7344410678],"iteration":899,"passed_time":72.56681515,"remaining_time":8.062979461},
{"learn":[0.7342372927],"iteration":900,"passed_time":72.64576918,"remaining_time":7.982165537},
{"learn":[0.7339888912],"iteration":901,"passed_time":72.7266924,"remaining_time":7.901569684},
{"learn":[0.7337642713],"iteration":902,"passed_time":72.80417246,"remaining_time":7.820603243},
{"learn":[0.7335567964],"iteration":903,"passed_time":72.88232737,"remaining_time":7.739716181},
{"learn":[0.7333161632],"iteration":904,"passed_time":72.96229988,"remaining_time":7.659025954},
{"learn":[0.7330080214],"iteration":905,"passed_time":73.04421491,"remaining_time":7.578538854},
{"learn":[0.732787806],"iteration":906,"passed_time":73.11669145,"remaining_time":7.497080821},
{"learn":[0.7326207273],"iteration":907,"passed_time":73.191081,"remaining_time":7.415836401},
{"learn":[0.7322766079],"iteration":908,"passed_time":73.2763565,"remaining_time":7.335696855},
{"learn":[0.7319356107],"iteration":909,"passed_time":73.36367008,"remaining_time":7.25574759},
{"learn":[0.7317421191],"iteration":910,"passed_time":73.43765898,"remaining_time":7.174480406},
{"learn":[0.7314676026],"iteration":911,"passed_time":73.51904404,"remaining_time":7.093942846},
{"learn":[0.7312268589],"iteration":912,"passed_time":73.59677564,"remaining_time":7.013055291},
{"learn":[0.7310452241],"iteration":913,"passed_time":73.67484443,"remaining_time":6.932206369},
{"learn":[0.7308499676],"iteration":914,"passed_time":73.75790129,"remaining_time":6.851826896},
{"learn":[0.7307050472],"iteration":915,"passed_time":73.83142189,"remaining_time":6.770567073},
{"learn":[0.7304382503],"iteration":916,"passed_time":73.90560905,"remaining_time":6.689384461},
{"learn":[0.7300728358],"iteration":917,"passed_time":73.98808366,"remaining_time":6.608957364},
{"learn":[0.7299563446],"iteration":918,"passed_time":74.07193416,"remaining_time":6.528647081},
{"learn":[0.7297850568],"iteration":919,"passed_time":74.14401397,"remaining_time":6.447305563},
{"learn":[0.7295563457],"iteration":920,"passed_time":74.2260654,"remaining_time":6.366839486},
{"learn":[0.7293283476],"iteration":921,"passed_time":74.30231933,"remaining_time":6.28587951},
{"learn":[0.7290451247],"iteration":922,"passed_time":74.38119714,"remaining_time":6.205148623},
{"learn":[0.7287696683],"iteration":923,"passed_time":74.46067726,"remaining_time":6.12447129},
{"learn":[0.7284010562],"iteration":924,"passed_time":74.5455046,"remaining_time":6.044230103},
{"learn":[0.7282482696],"iteration":925,"passed_time":74.62936073,"remaining_time":5.963901398},
{"learn":[0.7281191348],"iteration":926,"passed_time":74.70711972,"remaining_time":5.88308494},
{"learn":[0.7280008963],"iteration":927,"passed_time":74.78354288,"remaining_time":5.802171431},
{"learn":[0.7277483464],"iteration":928,"passed_time":74.86364666,"remaining_time":5.721548883},
{"learn":[0.7275483951],"iteration":929,"passed_time":74.94322713,"remaining_time":5.640888063},
{"learn":[0.7273486471],"iteration":930,"passed_time":75.01331984,"remaining_time":5.55952639},
{"learn":[0.7270560024],"iteration":931,"passed_time":75.09252501,"remaining_time":5.478853756},
{"learn":[0.726868585],"iteration":932,"passed_time":75.17193882,"remaining_time":5.398199251},
{"learn":[0.7266748008],"iteration":933,"passed_time":75.25104307,"remaining_time":5.317525528},
{"learn":[0.7264657457],"iteration":934,"passed_time":75.33093081,"remaining_time":5.236909629},
{"learn":[0.726189324],"iteration":935,"passed_time":75.4165558,"remaining_time":5.156687576},
{"learn":[0.7258760775],"iteration":936,"passed_time":75.50787545,"remaining_time":5.076836876},
{"learn":[0.7256315328],"iteration":937,"passed_time":75.59221388,"remaining_time":4.996500278},
{"learn":[0.7253570408],"iteration":938,"passed_time":75.6737992,"remaining_time":4.915976306},
{"learn":[0.725194577],"iteration":939,"passed_time":75.75131924,"remaining_time":4.83519059},
{"learn":[0.7249666695],"iteration":940,"passed_time":75.82377831,"remaining_time":4.754094495},
{"learn":[0.7247278462],"iteration":941,"passed_time":75.90319607,"remaining_time":4.673445193},
{"learn":[0.7244374441],"iteration":942,"passed_time":75.99115225,"remaining_time":4.593314611},
{"learn":[0.7242851833],"iteration":943,"passed_time":76.06367358,"remaining_time":4.512251823},
{"learn":[0.7240587703],"iteration":944,"passed_time":76.13563721,"remaining_time":4.431174653},
{"learn":[0.7238303856],"iteration":945,"passed_time":76.21028927,"remaining_time":4.350270212},
{"learn":[0.7235617233],"iteration":946,"passed_time":76.28881458,"remaining_time":4.269595747},
{"learn":[0.7232497307],"iteration":947,"passed_time":76.36221461,"remaining_time":4.188644683},
{"learn":[0.7230360037],"iteration":948,"passed_time":76.44514744,"remaining_time":4.108221833},
{"learn":[0.7227942069],"iteration":949,"passed_time":76.52494687,"remaining_time":4.027628783},
{"learn":[0.7226570003],"iteration":950,"passed_time":76.59399766,"remaining_time":3.946483581},
{"learn":[0.72230186],"iteration":951,"passed_time":76.67351678,"remaining_time":3.865891603},
{"learn":[0.722092144],"iteration":952,"passed_time":76.75443459,"remaining_time":3.785370856},
{"learn":[0.7219433287],"iteration":953,"passed_time":76.82893124,"remaining_time":3.704539662},
{"learn":[0.721695084],"iteration":954,"passed_time":76.90437318,"remaining_time":3.623766276},
{"learn":[0.7215211344],"iteration":955,"passed_time":76.97797377,"remaining_time":3.542919295},
{"learn":[0.7211983222],"iteration":956,"passed_time":77.05556885,"remaining_time":3.462266939},
{"learn":[0.7209299595],"iteration":957,"passed_time":77.13817359,"remaining_time":3.381840596},
{"learn":[0.7206392964],"iteration":958,"passed_time":77.21638845,"remaining_time":3.30122203},
{"learn":[0.7204598402],"iteration":959,"passed_time":77.28434042,"remaining_time":3.220180851},
{"learn":[0.720313192],"iteration":960,"passed_time":77.35841961,"remaining_time":3.139415572},
{"learn":[0.7201089581],"iteration":961,"passed_time":77.4368806,"remaining_time":3.058837279},
{"learn":[0.7198157669],"iteration":962,"passed_time":77.51404201,"remaining_time":2.978213452},
{"learn":[0.719659537],"iteration":963,"passed_time":77.59479554,"remaining_time":2.897730954},
{"learn":[0.7194254564],"iteration":964,"passed_time":77.67669611,"remaining_time":2.817289496},
{"learn":[0.7191068519],"iteration":965,"passed_time":77.75431013,"remaining_time":2.736694145},
{"learn":[0.7189682023],"iteration":966,"passed_time":77.82831627,"remaining_time":2.655981837},
{"learn":[0.7187673889],"iteration":967,"passed_time":77.90376137,"remaining_time":2.575330954},
{"learn":[0.7185804364],"iteration":968,"passed_time":77.97511194,"remaining_time":2.494559825},
{"learn":[0.7182240616],"iteration":969,"passed_time":78.06182764,"remaining_time":2.414283329},
{"learn":[0.7178600059],"iteration":970,"passed_time":78.14664172,"remaining_time":2.333936777},
{"learn":[0.7175101227],"iteration":971,"passed_time":78.23604528,"remaining_time":2.253713239},
{"learn":[0.7172283102],"iteration":972,"passed_time":78.31389167,"remaining_time":2.173150129},
{"learn":[0.7169642205],"iteration":973,"passed_time":78.39281642,"remaining_time":2.092621383},
{"learn":[0.7167411699],"iteration":974,"passed_time":78.48022566,"remaining_time":2.012313478},
{"learn":[0.7166474227],"iteration":975,"passed_time":78.55632078,"remaining_time":1.931712806},
{"learn":[0.7164821486],"iteration":976,"passed_time":78.63210692,"remaining_time":1.851114083},
{"learn":[0.7161240921],"iteration":977,"passed_time":78.71356832,"remaining_time":1.770652866},
{"learn":[0.7159170698],"iteration":978,"passed_time":78.79421337,"remaining_time":1.690172095},
{"learn":[0.7156622337],"iteration":979,"passed_time":78.88271877,"remaining_time":1.609851403},
{"learn":[0.7154239788],"iteration":980,"passed_time":78.98843157,"remaining_time":1.529847299},
{"learn":[0.7151448952],"iteration":981,"passed_time":79.10564645,"remaining_time":1.450001666},
{"learn":[0.7148511221],"iteration":982,"passed_time":79.23804788,"remaining_time":1.370342639},
{"learn":[0.714723903],"iteration":983,"passed_time":79.34896228,"remaining_time":1.290227029},
{"learn":[0.7145501001],"iteration":984,"passed_time":79.43373885,"remaining_time":1.209650845},
{"learn":[0.7142000808],"iteration":985,"passed_time":79.5329437,"remaining_time":1.129271006},
{"learn":[0.7139370084],"iteration":986,"passed_time":79.63489984,"remaining_time":1.048889258},
{"learn":[0.7135860009],"iteration":987,"passed_time":79.73637842,"remaining_time":0.9684580375},
{"learn":[0.7133500344],"iteration":988,"passed_time":79.82635651,"remaining_time":0.8878563413},
{"learn":[0.7130998431],"iteration":989,"passed_time":79.9284706,"remaining_time":0.8073582889},
{"learn":[0.7128355641],"iteration":990,"passed_time":80.012765,"remaining_time":0.726654778},
{"learn":[0.7126071151],"iteration":991,"passed_time":80.08891728,"remaining_time":0.6458783651},
{"learn":[0.7124446606],"iteration":992,"passed_time":80.17101821,"remaining_time":0.5651531999},
{"learn":[0.7121798975],"iteration":993,"passed_time":80.2564692,"remaining_time":0.4844454881},
{"learn":[0.7119698201],"iteration":994,"passed_time":80.32886432,"remaining_time":0.4036626348},
{"learn":[0.7117623015],"iteration":995,"passed_time":80.40400162,"remaining_time":0.322907637},
{"learn":[0.7114584611],"iteration":996,"passed_time":80.48396704,"remaining_time":0.2421784364},
{"learn":[0.7111982505],"iteration":997,"passed_time":80.56857212,"remaining_time":0.1614600644},
{"learn":[0.7110608922],"iteration":998,"passed_time":80.64782308,"remaining_time":0.08072855163},
{"learn":[0.7107528846],"iteration":999,"passed_time":80.73254232,"remaining_time":0}
]}